{
  "file_name": "HOUSE_OVERSIGHT_010753.jpg",
  "image_analysis": {
    "type": "document",
    "description": "This is a legal document titled 'CERTIFICATE OF SERVICE' from a court case. It certifies that a document was served to all counsel and parties of record via electronic filing. The document includes a 'SERVICE LIST' with contact information for attorneys representing different parties. The page is numbered 19 of 19 and has a Bates stamp in the bottom right corner.",
    "layout": "The document has a header with case information, a centered title, a main body of text, a signature line, a two-column service list, and a footer with a page number and a document identifier.",
    "quality": "high",
    "orientation": "portrait"
  },
  "text_extraction": {
    "full_text": "Case 9:08-cv-80736-KAM Document 306 Entered on FLSD Docket 02/02/2015 Page 19 of 19\n\nCERTIFICATE OF SERVICE\n\nI hereby certify that a true and correct copy of the foregoing was served by Notice of\nElectronic Filing generated by CM/ECF, on this 2nd day of February, 2015, on all counsel or\nparties of record on the Service List below.\n\n/s/ Kendall Coffey\n\nSERVICE LIST\n\nBradley J. Edwards\nFARMER, JAFFE, WEISSING,\nEDWARDS, FISTOS & LEHRMAN, P.L.\n425 North Andrews Avenue, Suite 2\nFort Lauderdale, Florida 33301\nTelephone (954) 524-2820\nFacsimile (954) 524-2822\nE-mail: brad@pathtojustice.com\n\nand\n\nPaul G. Cassell\nPro Hac Vice\nS.J. Quinney College of Law at the\nUniversity of Utah\n332 S. 1400 E.\nSalt Lake City, UT 84112\nTelephone: 801-585-5202\nFacsimile: 801-585-6833\nE-Mail: cassellp@law.utah.edu\n\nAttorneys for Jane Doe #1, 2, 3, and 4\n\nDexter Lee\nA. Marie Villafaña\nUNITED STATES ATTORNEY'S OFFICE\n500 S. Australian Ave., Suite 400\nWest Palm Beach, FL 33401\n(561) 820-8711\nFax: (561) 820-8777\nE-mail: Dexter.Lee@usdoj.gov\nE-mail: ann.marie.c.villafana@usdoj.gov\n\nAttorneys for the Government\n\n19\n\nHOUSE_OVERSIGHT_010753",
    "text_regions": [
      {
        "region": "header",
        "text": "Case 9:08-cv-80736-KAM Document 306 Entered on FLSD Docket 02/02/2015 Page 19 of 19",
        "type": "printed"
      },
      {
        "region": "body",
        "text": "CERTIFICATE OF SERVICE\n\nI hereby certify that a true and correct copy of the foregoing was served by Notice of\nElectronic Filing generated by CM/ECF, on this 2nd day of February, 2015, on all counsel or\nparties of record on the Service List below.",
        "type": "printed"
      },
      {
        "region": "signature",
        "text": "/s/ Kendall Coffey",
        "type": "printed"
      },
      {
        "region": "body",
        "text": "SERVICE LIST\n\nBradley J. Edwards\nFARMER, JAFFE, WEISSING,\nEDWARDS, FISTOS & LEHRMAN, P.L.\n425 North Andrews Avenue, Suite 2\nFort Lauderdale, Florida 33301\nTelephone (954) 524-2820\nFacsimile (954) 524-2822\nE-mail: brad@pathtojustice.com\n\nand\n\nPaul G. Cassell\nPro Hac Vice\nS.J. Quinney College of Law at the\nUniversity of Utah\n332 S. 1400 E.\nSalt Lake City, UT 84112\nTelephone: 801-585-5202\nFacsimile: 801-585-6833\nE-Mail: cassellp@law.utah.edu\n\nAttorneys for Jane Doe #1, 2, 3, and 4",
        "type": "printed"
      },
      {
        "region": "body",
        "text": "Dexter Lee\nA. Marie Villafaña\nUNITED STATES ATTORNEY'S OFFICE\n500 S. Australian Ave., Suite 400\nWest Palm Beach, FL 33401\n(561) 820-8711\nFax: (561) 820-8777\nE-mail: Dexter.Lee@usdoj.gov\nE-mail: ann.marie.c.villafana@usdoj.gov\n\nAttorneys for the Government",
        "type": "printed"
      },
      {
        "region": "footer",
        "text": "19",
        "type": "printed"
      },
      {
        "region": "footer",
        "text": "HOUSE_OVERSIGHT_010753",
        "type": "printed"
      }
    ]
  },
  "structured_data": {
    "dates": [
      "2015-02-02"
    ],
    "people": [
      "Kendall Coffey",
      "Bradley J. Edwards",
      "Paul G. Cassell",
      "Dexter Lee",
      "A. Marie Villafaña"
    ],
    "organizations": [
      "FARMER, JAFFE, WEISSING, EDWARDS, FISTOS & LEHRMAN, P.L.",
      "S.J. Quinney College of Law at the University of Utah",
      "UNITED STATES ATTORNEY'S OFFICE",
      "HOUSE_OVERSIGHT"
    ],
    "locations": [
      "Fort Lauderdale, Florida",
      "West Palm Beach, FL",
      "Salt Lake City, UT"
    ],
    "document_numbers": [
      "Case 9:08-cv-80736-KAM",
      "Document 306",
      "Page 19 of 19",
      "HOUSE_OVERSIGHT_010753"
    ],
    "financial_amounts": [],
    "contact_info": {
      "phone_numbers": [
        "(954) 524-2820",
        "801-585-5202",
        "(561) 820-8711",
        "(954) 524-2822",
        "801-585-6833",
        "(561) 820-8777"
      ],
      "email_addresses": [
        "brad@pathtojustice.com",
        "cassellp@law.utah.edu",
        "Dexter.Lee@usdoj.gov",
        "ann.marie.c.villafana@usdoj.gov"
      ],
      "addresses": [
        "425 North Andrews Avenue, Suite 2\nFort Lauderdale, Florida 33301",
        "332 S. 1400 E.\nSalt Lake City, UT 84112",
        "500 S. Australian Ave., Suite 400\nWest Palm Beach, FL 33401"
      ]
    },
    "signatures": [
      "/s/ Kendall Coffey"
    ],
    "stamps_or_markings": [
      "Bates stamp: HOUSE_OVERSIGHT_010753"
    ]
  },
  "document_metadata": {
    "document_type": "Certificate of Service",
    "sender": "Kendall Coffey",
    "recipient": "Parties on the Service List",
    "subject": "Service of a legal document in case 9:08-cv-80736-KAM.",
    "date": "2015-02-02",
    "references": [
      "Case 9:08-cv-80736-KAM",
      "Document 306"
    ]
  },
  "confidence": {
    "text_extraction": 0.99,
    "structured_data": 0.98,
    "overall": 0.98
  },
  "notes": "The document identifies attorneys for 'Jane Doe #1, 2, 3, and 4' and 'the Government'.",
  "file_path": "IMAGES\\001\\HOUSE_OVERSIGHT_010753.jpg",
  "house_oversight_id": "010753",
  "processing_metadata": {
    "processed_at": "2025-11-14T02:14:39.447584Z",
    "model": "gemini-2.5-pro"
  }
}