{
  "file_name": "HOUSE_OVERSIGHT_010658.jpg",
  "image_analysis": {
    "type": "document",
    "description": "The image is a scanned copy of page 42 of a financial disclosure form, specifically an OGE Form 278e. The form is filled out for Donald J. Trump and details 'Part 6: Other Assets and Income'. It is a table listing various financial assets, their value range, income type, and income amount range. The document is clean, with all text being printed and clearly legible.",
    "layout": "The document has a header containing the form title, instructions, filer's name, and page number. The main body is a table with columns for item number, description, EIF, value, income type, and income amount. A footer at the bottom provides the reporting date and a document identifier.",
    "quality": "high",
    "orientation": "portrait"
  },
  "text_extraction": {
    "full_text": "OGE Form 278e (March 2014)\nInstructions for Part 6\nNote: This is a public form. Do not include account numbers, street addresses, or family member names. See Instructions for required information.\nFiler's Name\nDonald J. Trump\nPage Number\n42 of 51\nPart 6: Other Assets and Income\n#\nDescription\nEIF\nValue\nIncome Type\nIncome Amount\n5\nBANK OF NOVA SCOTIA\nN/A\nNone (or less than $1,001)\nInterest, Capital Gain\n$2,501 - $5,000\n6\nBERKSHIRE HATHAWAY FIN\nN/A\nNone (or less than $1,001)\nInterest, Capital Gain\n$2,501 - $5,000\n7\nBHP BILLITON FIN USA LTD\nN/A\nNone (or less than $1,001)\nInterest, Capital Gain\n$5,001 - $15,000\n8\nCATERPILLAR FIN SERV CRP\nN/A\nNone (or less than $1,001)\nInterest, Capital Gain\n$2,501 - $5,000\n9\nCHEVRON CORP\nN/A\nNone (or less than $1,001)\nInterest, Capital Gain\n$2,501 - $5,000\n10\nCITIGROUP INC\nN/A\nNone (or less than $1,001)\nInterest, Capital Gain\n$5,001 - $15,000\n11\nCONAGRA INC\nN/A\nNone (or less than $1,001)\nInterest, Capital Gain\n$201 - $1,000\n12\nCREDIT SUISSE NEW YORK\nN/A\nNone (or less than $1,001)\nInterest, Capital Gain\n$2,501 - $5,000\n13\nDEUTSCHE GOVERNMENT MONEY MARKET\nN/A\nNone (or less than $1,001)\nDividends, Capital Gain\n$5,001 - $15,000\n14\nDEUTSCHE MONEY MARKET SERIES\nN/A\nNone (or less than $1,001)\nInterest, Capital Gain\n$201 - $1,000\n15\nECOLAB INC DTD 12/8/2011\nN/A\nNone (or less than $1,001)\nInterest, Capital Gain\n$5,001 - $15,000\n16\nEXXON MOBIL CORPORATION\nN/A\nNone (or less than $1,001)\nInterest, Capital Gain\n$2,501 - $5,000\n17\nFHLB DTD 7/25/2016 0.00%\nN/A\nNone (or less than $1,001)\nInterest, Capital Gain\n$2,501 - $5,000\n18\nFMCC DTD 8/7/2012 2.50%\nN/A\nNone (or less than $1,001)\nInterest, Capital Gain\n$201 - $1,000\n19\nFNMA DTD 1/29/1999 0.00%\nN/A\nNone (or less than $1,001)\nInterest, Capital Gain\n$201 - $1,000\n20\nFORD MTR DTD 12/18/2006\nN/A\nNone (or less than $1,001)\nInterest, Capital Gain\n$5,001 - $15,000\n21\nGOLDMAN SACHS GROUP INC\nN/A\nNone (or less than $1,001)\nInterest, Capital Gain\n$15,001 - $50,000\n22\nIBM CORP\nN/A\nNone (or less than $1,001)\nInterest, Capital Gain\n$2,501 - $5,000\nInformation being reported is as of April 15, 2017.\nHOUSE_OVERSIGHT_010658",
    "text_regions": [
      {
        "region": "header",
        "text": "OGE Form 278e (March 2014)\nInstructions for Part 6\nNote: This is a public form. Do not include account numbers, street addresses, or family member names. See Instructions for required information.",
        "type": "printed"
      },
      {
        "region": "header",
        "text": "Filer's Name\nDonald J. Trump",
        "type": "printed"
      },
      {
        "region": "header",
        "text": "Page Number\n42 of 51",
        "type": "printed"
      },
      {
        "region": "body",
        "text": "Part 6: Other Assets and Income\n#\nDescription\nEIF\nValue\nIncome Type\nIncome Amount\n5\nBANK OF NOVA SCOTIA\nN/A\nNone (or less than $1,001)\nInterest, Capital Gain\n$2,501 - $5,000\n6\nBERKSHIRE HATHAWAY FIN\nN/A\nNone (or less than $1,001)\nInterest, Capital Gain\n$2,501 - $5,000\n7\nBHP BILLITON FIN USA LTD\nN/A\nNone (or less than $1,001)\nInterest, Capital Gain\n$5,001 - $15,000\n8\nCATERPILLAR FIN SERV CRP\nN/A\nNone (or less than $1,001)\nInterest, Capital Gain\n$2,501 - $5,000\n9\nCHEVRON CORP\nN/A\nNone (or less than $1,001)\nInterest, Capital Gain\n$2,501 - $5,000\n10\nCITIGROUP INC\nN/A\nNone (or less than $1,001)\nInterest, Capital Gain\n$5,001 - $15,000\n11\nCONAGRA INC\nN/A\nNone (or less than $1,001)\nInterest, Capital Gain\n$201 - $1,000\n12\nCREDIT SUISSE NEW YORK\nN/A\nNone (or less than $1,001)\nInterest, Capital Gain\n$2,501 - $5,000\n13\nDEUTSCHE GOVERNMENT MONEY MARKET\nN/A\nNone (or less than $1,001)\nDividends, Capital Gain\n$5,001 - $15,000\n14\nDEUTSCHE MONEY MARKET SERIES\nN/A\nNone (or less than $1,001)\nInterest, Capital Gain\n$201 - $1,000\n15\nECOLAB INC DTD 12/8/2011\nN/A\nNone (or less than $1,001)\nInterest, Capital Gain\n$5,001 - $15,000\n16\nEXXON MOBIL CORPORATION\nN/A\nNone (or less than $1,001)\nInterest, Capital Gain\n$2,501 - $5,000\n17\nFHLB DTD 7/25/2016 0.00%\nN/A\nNone (or less than $1,001)\nInterest, Capital Gain\n$2,501 - $5,000\n18\nFMCC DTD 8/7/2012 2.50%\nN/A\nNone (or less than $1,001)\nInterest, Capital Gain\n$201 - $1,000\n19\nFNMA DTD 1/29/1999 0.00%\nN/A\nNone (or less than $1,001)\nInterest, Capital Gain\n$201 - $1,000\n20\nFORD MTR DTD 12/18/2006\nN/A\nNone (or less than $1,001)\nInterest, Capital Gain\n$5,001 - $15,000\n21\nGOLDMAN SACHS GROUP INC\nN/A\nNone (or less than $1,001)\nInterest, Capital Gain\n$15,001 - $50,000\n22\nIBM CORP\nN/A\nNone (or less than $1,001)\nInterest, Capital Gain\n$2,501 - $5,000",
        "type": "printed"
      },
      {
        "region": "footer",
        "text": "Information being reported is as of April 15, 2017.",
        "type": "printed"
      },
      {
        "region": "footer",
        "text": "HOUSE_OVERSIGHT_010658",
        "type": "printed"
      }
    ]
  },
  "structured_data": {
    "dates": [
      "2014-03",
      "2017-04-15",
      "2011-12-08",
      "2016-07-25",
      "2012-08-07",
      "1999-01-29",
      "2006-12-18"
    ],
    "people": [
      "Donald J. Trump"
    ],
    "organizations": [
      "BANK OF NOVA SCOTIA",
      "BERKSHIRE HATHAWAY FIN",
      "BHP BILLITON FIN USA LTD",
      "CATERPILLAR FIN SERV CRP",
      "CHEVRON CORP",
      "CITIGROUP INC",
      "CONAGRA INC",
      "CREDIT SUISSE NEW YORK",
      "DEUTSCHE GOVERNMENT MONEY MARKET",
      "DEUTSCHE MONEY MARKET SERIES",
      "ECOLAB INC",
      "EXXON MOBIL CORPORATION",
      "FHLB",
      "FMCC",
      "FNMA",
      "FORD MTR",
      "GOLDMAN SACHS GROUP INC",
      "IBM CORP"
    ],
    "locations": [],
    "document_numbers": [
      "OGE Form 278e",
      "42 of 51",
      "HOUSE_OVERSIGHT_010658"
    ],
    "financial_amounts": [
      "None (or less than $1,001)",
      "$2,501 - $5,000",
      "$5,001 - $15,000",
      "$201 - $1,000",
      "$15,001 - $50,000"
    ],
    "contact_info": {
      "phone_numbers": [],
      "email_addresses": [],
      "addresses": []
    },
    "signatures": [],
    "stamps_or_markings": []
  },
  "document_metadata": {
    "document_type": "form",
    "sender": null,
    "recipient": null,
    "subject": "Part 6: Other Assets and Income for Donald J. Trump",
    "date": "2017-04-15",
    "references": [
      "HOUSE_OVERSIGHT_010658"
    ]
  },
  "confidence": {
    "text_extraction": 0.99,
    "structured_data": 0.98,
    "overall": 0.98
  },
  "notes": "The document is a financial disclosure form. All financial values are given in ranges, not as exact figures. The 'Value' for all listed assets is 'None (or less than $1,001)', which typically refers to the value of the asset itself at the end of the reporting period, while the 'Income Amount' refers to the income generated by that asset during the period.",
  "file_path": "IMAGES\\001\\HOUSE_OVERSIGHT_010658.jpg",
  "house_oversight_id": "010658",
  "processing_metadata": {
    "processed_at": "2025-11-14T01:14:16.430326Z",
    "model": "gemini-2.5-pro"
  }
}