{
  "file_name": "HOUSE_OVERSIGHT_010477-010485.txt",
  "content": {
    "full_text": "iiiIERFUL BILLIONAIRE, \n- EX SCANDAL THAT UNDID HIM, AND ALL \nTHE JUSTICE THAT MONEY CAN BUY: \nTHE SHOCKING TRUE STORY OF JEFFREY EPSTEIN \nHOUSE OVERSIGHT 010477 \n'TERSON \nI don't see what it adds to the \n.,,stigation had taken place, that \njut, at that time, no criminal \nirs had been launched. And in \nthe rumors of Epstein's dealings \nto be just that—rumors. \nhis lawyers, his editors, and his \ning odd and disturbing happened \n:n in Times Square. \nto the office early. He swiped his \nthe elevator button, and arrived in \nion area on the twenty-first floor. \nct time to review Ward's story. \nn's town house—which is said to \nresidence in New York City at the \n1, amid the flurry of menservants \nand pristine white gloves, you feel \nLeone's private Xanadu,\" she'd writ-\nperson's home, but a high-walled, \nthat seems to have no boundaries. \n.ed not with paintings but with row \narned eyeballs; these, the owner tells \nnported from England, where they \n.rs. Next comes a marble foyer, which \ne manner of Jean Dubuffet , .. but the \nvisitors who painted it. In any case, \n150 \nOne of the photographs \ncaptured on video during the \nPalm Beach Police Department \nsearch warrant walk-through \nof Epstein's El Brillo Way \nresidence (Palm Beach Police \nDepartment) \n\nJeffrey Epstein, Coney Island, \ncirca 1969 (Anonymous) \n\nEpstein's Palm Beach \nproperty, 358 El Brill° \nWay (O Chris Bott / \nSplash News / Corbis) \n\nJeffrey Epstein's 1969 high school \nyearbook photo (Lafayette High \nSchool, Brooklyn, New York, 1969) \nHOUSE OVERSIGHT 010478 \nLeslie Wexner, photographed \nat his home in New York City, \n1989 (CD Lynn Goldsmith) \n\n(L to R) Jeffrey Epstein, Ghislaine \nMaxwell, and Tony Randall, who \npresided over a November 1991 \nYIVO Institute event at the Plaza \nHotel to honor the late Robert \nMaxwell (Marina Gamier) \n\nJeffrey Epstein, Donald \nTrump, and (newly signed \nTrump Model) \nattending the \nVictoria's Secret Angels \nparty at Laura Belle club \nin New York City on April \n8, 1997 (Marina Gamier) \n\n(L to R) \n, Jeffrey Epstein, \nGhislaine Maxwell, and \nattend a \nreception at Mar-a-Lago, \n1995. (Davidoff Studios) \nHOUSE OVERSIGHT 010479 \nlater, photographed \nLe in New York City, \n.ynn Goldsmith) \n\n(L to R) Deborah \nBlohm, Jeffrey Epstein, \nGhislaine Maxwell, and \nGwendolyn Beck attend a \nreception at Mar-a-Lago, \n1995. (Davidoff Studios) \n\nage \nfifteen; photo reportedly \ntaken by Jeffrey Epstein in \nNew York City \nAffidavit, US \nDistrict Southern Court of \nFlorida) \n\n(L to R) Prince Andrew, \nand Ghislaine Maxwell; photo reportedly \ntaken by Epstein with camera \nin Maxwell's London town house. \nwas seventeen years old at this \ntime. (r,iffidavit, US \nDistrict Southern Court of Florida.) \n\nage seventeen; \nphoto reportedly taken by \nJeffrey Epstein at Zorro Ranch, \nhis New Mexico iDronerty. \nin winter \nAffidavit, US District Southern \nCourt of Florida) \n\nJeffrey Epstein with Professor \nAlan Dershowitz in Cambridge, \nMA, September 8, 2004 (0 Rick \nFriedman / Corbis) \nHOUSE OVERSIGHT 010480 \nOn the day the police investigation \nbegan, Epstein was photographed \nwith Ghislaine Maxwell in New York \nCity at the 2005 WaIl Street concert \nseries benefiting Wall Street Rising, \nat Cipriani in New York City, March \n15, 2005. (Joe Shildhorn / Patrick \nMcMullen) \n\nJeffrey Epstein, photographed \nwith attend-\ning the launch of Radar \nmagazine held at the Hotel \nQT in New York City, May \n2005 (Neil Rasmus / Patrick-\nMcMullan. com / Sipa Press) \n\n2008 Palm Beach County Sheriff's Office \nbooking photo of Jeffrey Epstein (Palm \nBeach County Sheriff's Office) \n\nThe Stockade, where Epstein \n146 served his sentence, photog \n1:1 here in 2006, was located a \nFairgrounds Road in West Pal \nBeach, Florida. At the time, \nused as a minimum- and in \nsecurity facility housing WO \n, \njuveniles, as well as male to \non a work-release program. \nAerial Photos) \nHOUSE OVERSIGHT 010481 \ngation \n-aphed \nN York \n-oncert \nRising, \nMarch \nPatrick \nvfullen) \n\nJeffrey Epstein, photographed \nwith Adrianna Ross, attend-\ning the launch of Radar \nmagazine held at the Hotel \nQT in New York City, May \n2005 (Neil Rasmus / Patrick-\nMcMullan.com / Sipa Press) \n\nPs Office \nin (Palm \ni's Office) \n\nThe Stockade, where Epstein \n• served his sentence, photograph \nhere in 2006, was located at 673 \n• Fairgrounds Road in West Pal \nBeach, Florida. At the time, it \nused as a minimum- and media \nsecurity facility housing women \njuveniles, as well as male Mina \non a work-release program. (5 \nAerial Photos) \n\nEpstein pleaded guilty to state \nsolicitation charges and served \nthirteen months of an eighteen-\nmonth sentence, with liberal \nwork-release privileges, in a \nsolitary cell at the Palm Beach \nCounty Stockade similar to the \none pictured here, (Courtesy \nCDC Special Management, Palm \nBeach Sheriffs Office) \n\nJeffrey Epstein's entry in \nthe National Sex Offender \nRegistry (National Sex \nOffender Registry) \n\nEpstein and lawyer at the West \nPalm Beach courthouse in June \n2008 to enter a plea nearly two \nyears after being charged (Uma \nSanghvi / The Palm Beach Post / \nZUMAPRESS.com) \n\n\"IMF • MIMEO. \n•••••komp \n11.11111111 \nrio• \nlidsammun \nta.1.1.13,÷7.60W31-4. \noak: 1 \n\nEpstein's Little Saint James \nisland, U.S. Virgin Islands: a \nprivately owned cay (nicknamed \n• : Little Saint Jeff's) whose owner \nlocals affectionately refer to \nas Richie Rich (© Chris Bott / \nSplash News / Corbis) \nHOUSE OVERSIGHT 010482 \nEpstein's Gulfstream, \nphotographed on Little \nSaint James island in \nthe U.S. Virgin Islands, \nJanuary 2015 (0 Chris \nBott / Splash News I Corbis) \n\nf.„-011-04.tr-\n\nEpstein's longtime pilot, Larry Visos4 \nwas at the controls as Epstein's \nGulfstream left Teterboro Airport in \nNew Jersey, January 2016. (Jae Donnelly) \n\nWhen Prince Andrew and Epstein were seen \nNew York's Central \nstrolling together through  7- \nPark  in 2011, shortly after Epstein's release \nfrom jail, the duke was forced to quit his \nrole as the British government's global trade , \nenvoy. (Jae Donnelly / News of the World) —7 \n\nStephen Hawking, photographed \nin March 2006 aboard an Atlantis \nsubmarine that was custom-fitted \nby Epstein to accommodate his \nwheelchair. Hawking was attendin2, \nthe conference \"Confronting Gravin \n\"a workshop to explore fundanotii! \nquestions in physics and cosmolO• \nsponsored by the J. Epstein VI \nFoundation and the Center for \nEducation and Research in Cosra \nand Astrophysics (CERCA) at Oic \nWestern Reserve University, at thz \nCanton, St. Thomas, USVI. (Coterf.9 \nCERCA, Case Western LlniversitA.;: \nTaglia. \n°avies \n?or \nBall. \nHOUSE OVERSIGHT 010483 \n..• \nEpstein's longtime pilot, Larry Visoski, \n, \nIwas at the controls as Epstein's \nGulfstream left Teterboro Airport in \nNew Jersey, January 2016. (Jae Donnelly) \n\ne seen \n-entral \n-elease \nuit his \n1 trade \nWorld) \n\nStephen Hawking, photographed \nin March 2006 aboard an Atlantis \nsubmarine that was custom-fitted \nby Epstein to accommodate his \nwheelchair. Hawking was attending \n•.4 the conference \"Confronting Gravity. \n\"a workshop to explore fundamental \nquestions in physics and cosmoloo\" \nsponsored by the J. EpSteiti VI \nFoundation and the Center for \nEducation and Research in Costnolop \nand Astrophysics (CERCA) at Case \nWestern Reserve University, at the R;l1 \nCarlton, St. Thomas, LiSv). (Court0 \nCERCA, Case Western Univeis \n\nEpstein's current residence, the \nstoried building formerly known \nas the Herbert N. Straus Mansion, \non East list Street just off Central \nPark, was acquired by Leslie \nWexner in 1989. (Laura Hanifin) \n\nphotographed at the New \nlork Academy of Art's Tribeca \nBall, April 14, 2004 (Rob Rich / \nSocietyAllure.com) \n\nA framed photo of Florida governor \nCharlie Crist and Scott Rothstein in \nRothstein's office in Fort Lauderdale, \nautographed by Charlie Crist: Scott—\nYou are amazing! Charlie Crist \n(CarlineJean 0 Sun Sentinel / ZUMA-\nPRESS.com) \n\nEpstein, a longtime benefactor, with \nan unidentified friend, attended the \n'IN 2014 New York Academy of Art's \nTribeca Ball, presented by Van Cleef \n& Arpels, at the New York Academy \nof Art on April 7, 2014, in New York \nCity. (Billy Farrell IBFAnyc.com) \nHOUSE OVERSIGHT 010484 \nIf. 0) \n'1 re K V \nUMW and husband, \nNASCAR driver Brian Vickers, \narrive on the red carpet at the 141st \nrunning of the Kentucky Derby \nat Churchill Downs in Louisville, \nKentucky. (Jeff Moreland / Icon \nSportswire via AP Images) \n\nand Larry \nVisoski, Epstein's personal \npilot, in what appears to be \nthe cockpit of a Gulfstream \nG-II (YouTube) \n\nMichael and Janet Reiter at the Palm \nBeach Police Foundation Policemen's \nBall at Mar-a-Lago, January \n2012 (Debbie Schatz/ Palm Beach \nDaily News / ZUMAPRESS.com) \n\nRetired Palm Beach police \ndetective Joe Recarey, \nNovember 2013 (Megltan \nMcCarthy / Palm Beach Daily \nNews f ZUMAPRES.S.com) \n\nguests a \nture of a \nThe j \nMort Zu \nMicros() \namong I \nseveral c \nscientist \nShe'd ha \nwith Var \ninformal \nto form t \nIn th \nWha \nartist, hi \nswipe hi \nter saw a \nThe \nIt wa \nhis office \nEpstein \nnal char \ninclude \nwhen he \nShe'd \none of hi \nOn doct( \nHOUSE OVERSIGHT 010485 \n",
    "sections": [
      {
        "section_index": 0,
        "section_type": "header",
        "text": "iiiIERFUL BILLIONAIRE, \n- EX SCANDAL THAT UNDID HIM, AND ALL \nTHE JUSTICE THAT MONEY CAN BUY: \nTHE SHOCKING TRUE STORY OF JEFFREY EPSTEIN"
      },
      {
        "section_index": 1,
        "section_type": "document_control_number",
        "text": "HOUSE OVERSIGHT 010477"
      },
      {
        "section_index": 2,
        "section_type": "fragmented_paragraph",
        "text": "'TERSON \nI don't see what it adds to the \n.,,stigation had taken place, that \njut, at that time, no criminal \nirs had been launched. And in \nthe rumors of Epstein's dealings \nto be just that—rumors. \nhis lawyers, his editors, and his \ning odd and disturbing happened \n:n in Times Square. \nto the office early. He swiped his \nthe elevator button, and arrived in \nion area on the twenty-first floor. \nct time to review Ward's story. \nn's town house—which is said to \nresidence in New York City at the \n1, amid the flurry of menservants \nand pristine white gloves, you feel \nLeone's private Xanadu,\" she'd writ-\nperson's home, but a high-walled, \nthat seems to have no boundaries. \n.ed not with paintings but with row \narned eyeballs; these, the owner tells \nnported from England, where they \n.rs. Next comes a marble foyer, which \ne manner of Jean Dubuffet , .. but the \nvisitors who painted it. In any case, \n150"
      },
      {
        "section_index": 3,
        "section_type": "caption",
        "text": "One of the photographs \ncaptured on video during the \nPalm Beach Police Department \nsearch warrant walk-through \nof Epstein's El Brillo Way \nresidence (Palm Beach Police \nDepartment)"
      },
      {
        "section_index": 4,
        "section_type": "caption",
        "text": "Jeffrey Epstein, Coney Island, \ncirca 1969 (Anonymous)"
      },
      {
        "section_index": 5,
        "section_type": "caption",
        "text": "Epstein's Palm Beach \nproperty, 358 El Brill° \nWay (O Chris Bott / \nSplash News / Corbis)"
      },
      {
        "section_index": 6,
        "section_type": "caption",
        "text": "Jeffrey Epstein's 1969 high school \nyearbook photo (Lafayette High \nSchool, Brooklyn, New York, 1969)"
      },
      {
        "section_index": 7,
        "section_type": "document_control_number",
        "text": "HOUSE OVERSIGHT 010478"
      },
      {
        "section_index": 8,
        "section_type": "caption",
        "text": "Leslie Wexner, photographed \nat his home in New York City, \n1989 (CD Lynn Goldsmith)"
      },
      {
        "section_index": 9,
        "section_type": "caption",
        "text": "(L to R) Jeffrey Epstein, Ghislaine \nMaxwell, and Tony Randall, who \npresided over a November 1991 \nYIVO Institute event at the Plaza \nHotel to honor the late Robert \nMaxwell (Marina Gamier)"
      },
      {
        "section_index": 10,
        "section_type": "caption",
        "text": "Jeffrey Epstein, Donald \nTrump, and (newly signed \nTrump Model) \nattending the \nVictoria's Secret Angels \nparty at Laura Belle club \nin New York City on April \n8, 1997 (Marina Gamier)"
      },
      {
        "section_index": 11,
        "section_type": "caption",
        "text": "(L to R) \n, Jeffrey Epstein, \nGhislaine Maxwell, and \nattend a \nreception at Mar-a-Lago, \n1995. (Davidoff Studios)"
      },
      {
        "section_index": 12,
        "section_type": "document_control_number",
        "text": "HOUSE OVERSIGHT 010479"
      },
      {
        "section_index": 13,
        "section_type": "fragmented_caption",
        "text": "later, photographed \nLe in New York City, \n.ynn Goldsmith)"
      },
      {
        "section_index": 14,
        "section_type": "caption",
        "text": "(L to R) Deborah \nBlohm, Jeffrey Epstein, \nGhislaine Maxwell, and \nGwendolyn Beck attend a \nreception at Mar-a-Lago, \n1995. (Davidoff Studios)"
      },
      {
        "section_index": 15,
        "section_type": "caption",
        "text": "age \nfifteen; photo reportedly \ntaken by Jeffrey Epstein in \nNew York City \nAffidavit, US \nDistrict Southern Court of \nFlorida)"
      },
      {
        "section_index": 16,
        "section_type": "caption",
        "text": "(L to R) Prince Andrew, \nand Ghislaine Maxwell; photo reportedly \ntaken by Epstein with camera \nin Maxwell's London town house. \nwas seventeen years old at this \ntime. (r,iffidavit, US \nDistrict Southern Court of Florida.)"
      },
      {
        "section_index": 17,
        "section_type": "caption",
        "text": "age seventeen; \nphoto reportedly taken by \nJeffrey Epstein at Zorro Ranch, \nhis New Mexico iDronerty. \nin winter \nAffidavit, US District Southern \nCourt of Florida)"
      },
      {
        "section_index": 18,
        "section_type": "caption",
        "text": "Jeffrey Epstein with Professor \nAlan Dershowitz in Cambridge, \nMA, September 8, 2004 (0 Rick \nFriedman / Corbis)"
      },
      {
        "section_index": 19,
        "section_type": "document_control_number",
        "text": "HOUSE OVERSIGHT 010480"
      },
      {
        "section_index": 20,
        "section_type": "caption",
        "text": "On the day the police investigation \nbegan, Epstein was photographed \nwith Ghislaine Maxwell in New York \nCity at the 2005 WaIl Street concert \nseries benefiting Wall Street Rising, \nat Cipriani in New York City, March \n15, 2005. (Joe Shildhorn / Patrick \nMcMullen)"
      },
      {
        "section_index": 21,
        "section_type": "caption",
        "text": "Jeffrey Epstein, photographed \nwith attend-\ning the launch of Radar \nmagazine held at the Hotel \nQT in New York City, May \n2005 (Neil Rasmus / Patrick-\nMcMullan. com / Sipa Press)"
      },
      {
        "section_index": 22,
        "section_type": "caption",
        "text": "2008 Palm Beach County Sheriff's Office \nbooking photo of Jeffrey Epstein (Palm \nBeach County Sheriff's Office)"
      },
      {
        "section_index": 23,
        "section_type": "caption",
        "text": "The Stockade, where Epstein \n146 served his sentence, photog \n1:1 here in 2006, was located a \nFairgrounds Road in West Pal \nBeach, Florida. At the time, \nused as a minimum- and in \nsecurity facility housing WO \n, \njuveniles, as well as male to \non a work-release program. \nAerial Photos)"
      },
      {
        "section_index": 24,
        "section_type": "document_control_number",
        "text": "HOUSE OVERSIGHT 010481"
      },
      {
        "section_index": 25,
        "section_type": "fragmented_caption",
        "text": "gation \n-aphed \nN York \n-oncert \nRising, \nMarch \nPatrick \nvfullen)"
      },
      {
        "section_index": 26,
        "section_type": "caption",
        "text": "Jeffrey Epstein, photographed \nwith Adrianna Ross, attend-\ning the launch of Radar \nmagazine held at the Hotel \nQT in New York City, May \n2005 (Neil Rasmus / Patrick-\nMcMullan.com / Sipa Press)"
      },
      {
        "section_index": 27,
        "section_type": "fragmented_caption",
        "text": "Ps Office \nin (Palm \ni's Office)"
      },
      {
        "section_index": 28,
        "section_type": "caption",
        "text": "The Stockade, where Epstein \n• served his sentence, photograph \nhere in 2006, was located at 673 \n• Fairgrounds Road in West Pal \nBeach, Florida. At the time, it \nused as a minimum- and media \nsecurity facility housing women \njuveniles, as well as male Mina \non a work-release program. (5 \nAerial Photos)"
      },
      {
        "section_index": 29,
        "section_type": "caption",
        "text": "Epstein pleaded guilty to state \nsolicitation charges and served \nthirteen months of an eighteen-\nmonth sentence, with liberal \nwork-release privileges, in a \nsolitary cell at the Palm Beach \nCounty Stockade similar to the \none pictured here, (Courtesy \nCDC Special Management, Palm \nBeach Sheriffs Office)"
      },
      {
        "section_index": 30,
        "section_type": "caption",
        "text": "Jeffrey Epstein's entry in \nthe National Sex Offender \nRegistry (National Sex \nOffender Registry)"
      },
      {
        "section_index": 31,
        "section_type": "caption",
        "text": "Epstein and lawyer at the West \nPalm Beach courthouse in June \n2008 to enter a plea nearly two \nyears after being charged (Uma \nSanghvi / The Palm Beach Post / \nZUMAPRESS.com)"
      },
      {
        "section_index": 32,
        "section_type": "unclear_text",
        "text": "\"IMF • MIMEO. \n•••••komp \n11.11111111 \nrio• \nlidsammun \nta.1.1.13,÷7.60W31-4. \noak: 1"
      },
      {
        "section_index": 33,
        "section_type": "caption",
        "text": "Epstein's Little Saint James \nisland, U.S. Virgin Islands: a \nprivately owned cay (nicknamed \n• : Little Saint Jeff's) whose owner \nlocals affectionately refer to \nas Richie Rich (© Chris Bott / \nSplash News / Corbis)"
      },
      {
        "section_index": 34,
        "section_type": "document_control_number",
        "text": "HOUSE OVERSIGHT 010482"
      },
      {
        "section_index": 35,
        "section_type": "caption",
        "text": "Epstein's Gulfstream, \nphotographed on Little \nSaint James island in \nthe U.S. Virgin Islands, \nJanuary 2015 (0 Chris \nBott / Splash News I Corbis)"
      },
      {
        "section_index": 36,
        "section_type": "unclear_text",
        "text": "f.„-011-04.tr-"
      },
      {
        "section_index": 37,
        "section_type": "caption",
        "text": "Epstein's longtime pilot, Larry Visos4 \nwas at the controls as Epstein's \nGulfstream left Teterboro Airport in \nNew Jersey, January 2016. (Jae Donnelly)"
      },
      {
        "section_index": 38,
        "section_type": "caption",
        "text": "When Prince Andrew and Epstein were seen \nNew York's Central \nstrolling together through  7- \nPark  in 2011, shortly after Epstein's release \nfrom jail, the duke was forced to quit his \nrole as the British government's global trade , \nenvoy. (Jae Donnelly / News of the World) —7"
      },
      {
        "section_index": 39,
        "section_type": "caption",
        "text": "Stephen Hawking, photographed \nin March 2006 aboard an Atlantis \nsubmarine that was custom-fitted \nby Epstein to accommodate his \nwheelchair. Hawking was attendin2, \nthe conference \"Confronting Gravin \n\"a workshop to explore fundanotii! \nquestions in physics and cosmolO• \nsponsored by the J. Epstein VI \nFoundation and the Center for \nEducation and Research in Cosra \nand Astrophysics (CERCA) at Oic \nWestern Reserve University, at thz \nCanton, St. Thomas, USVI. (Coterf.9 \nCERCA, Case Western LlniversitA.;: \nTaglia. \n°avies \n?or \nBall."
      },
      {
        "section_index": 40,
        "section_type": "document_control_number",
        "text": "HOUSE OVERSIGHT 010483"
      },
      {
        "section_index": 41,
        "section_type": "fragmented_caption",
        "text": "..• \nEpstein's longtime pilot, Larry Visoski, \n, \nIwas at the controls as Epstein's \nGulfstream left Teterboro Airport in \nNew Jersey, January 2016. (Jae Donnelly)"
      },
      {
        "section_index": 42,
        "section_type": "fragmented_caption",
        "text": "e seen \n-entral \n-elease \nuit his \n1 trade \nWorld)"
      },
      {
        "section_index": 43,
        "section_type": "caption",
        "text": "Stephen Hawking, photographed \nin March 2006 aboard an Atlantis \nsubmarine that was custom-fitted \nby Epstein to accommodate his \nwheelchair. Hawking was attending \n•.4 the conference \"Confronting Gravity. \n\"a workshop to explore fundamental \nquestions in physics and cosmoloo\" \nsponsored by the J. EpSteiti VI \nFoundation and the Center for \nEducation and Research in Costnolop \nand Astrophysics (CERCA) at Case \nWestern Reserve University, at the R;l1 \nCarlton, St. Thomas, LiSv). (Court0 \nCERCA, Case Western Univeis"
      },
      {
        "section_index": 44,
        "section_type": "caption",
        "text": "Epstein's current residence, the \nstoried building formerly known \nas the Herbert N. Straus Mansion, \non East list Street just off Central \nPark, was acquired by Leslie \nWexner in 1989. (Laura Hanifin)"
      },
      {
        "section_index": 45,
        "section_type": "caption",
        "text": "photographed at the New \nlork Academy of Art's Tribeca \nBall, April 14, 2004 (Rob Rich / \nSocietyAllure.com)"
      },
      {
        "section_index": 46,
        "section_type": "caption",
        "text": "A framed photo of Florida governor \nCharlie Crist and Scott Rothstein in \nRothstein's office in Fort Lauderdale, \nautographed by Charlie Crist: Scott—\nYou are amazing! Charlie Crist \n(CarlineJean 0 Sun Sentinel / ZUMA-\nPRESS.com)"
      },
      {
        "section_index": 47,
        "section_type": "caption",
        "text": "Epstein, a longtime benefactor, with \nan unidentified friend, attended the \n'IN 2014 New York Academy of Art's \nTribeca Ball, presented by Van Cleef \n& Arpels, at the New York Academy \nof Art on April 7, 2014, in New York \nCity. (Billy Farrell IBFAnyc.com)"
      },
      {
        "section_index": 48,
        "section_type": "document_control_number",
        "text": "HOUSE OVERSIGHT 010484"
      },
      {
        "section_index": 49,
        "section_type": "fragmented_caption",
        "text": "If. 0) \n'1 re K V \nUMW and husband, \nNASCAR driver Brian Vickers, \narrive on the red carpet at the 141st \nrunning of the Kentucky Derby \nat Churchill Downs in Louisville, \nKentucky. (Jeff Moreland / Icon \nSportswire via AP Images)"
      },
      {
        "section_index": 50,
        "section_type": "caption",
        "text": "and Larry \nVisoski, Epstein's personal \npilot, in what appears to be \nthe cockpit of a Gulfstream \nG-II (YouTube)"
      },
      {
        "section_index": 51,
        "section_type": "caption",
        "text": "Michael and Janet Reiter at the Palm \nBeach Police Foundation Policemen's \nBall at Mar-a-Lago, January \n2012 (Debbie Schatz/ Palm Beach \nDaily News / ZUMAPRESS.com)"
      },
      {
        "section_index": 52,
        "section_type": "caption",
        "text": "Retired Palm Beach police \ndetective Joe Recarey, \nNovember 2013 (Megltan \nMcCarthy / Palm Beach Daily \nNews f ZUMAPRES.S.com)"
      },
      {
        "section_index": 53,
        "section_type": "fragmented_paragraph",
        "text": "guests a \nture of a \nThe j \nMort Zu \nMicros() \namong I \nseveral c \nscientist \nShe'd ha \nwith Var \ninformal \nto form t \nIn th \nWha \nartist, hi \nswipe hi \nter saw a \nThe \nIt wa \nhis office \nEpstein \nnal char \ninclude \nwhen he \nShe'd \none of hi \nOn doct("
      },
      {
        "section_index": 54,
        "section_type": "document_control_number",
        "text": "HOUSE OVERSIGHT 010485"
      }
    ]
  },
  "metadata": {
    "document_type": "Book/Report Excerpt (Photo Section)",
    "participants": [
      "Jeffrey Epstein",
      "Ghislaine Maxwell",
      "Leslie Wexner",
      "Tony Randall",
      "Robert Maxwell",
      "Donald Trump",
      "Deborah Blohm",
      "Gwendolyn Beck",
      "Prince Andrew",
      "Alan Dershowitz",
      "Adrianna Ross",
      "Larry Visoski",
      "Stephen Hawking",
      "Charlie Crist",
      "Scott Rothstein",
      "Brian Vickers",
      "Michael Reiter",
      "Janet Reiter",
      "Joe Recarey",
      "Jean Dubuffet"
    ],
    "date_range": {
      "earliest": "circa 1969",
      "latest": "January 2016"
    },
    "file_references": [
      "HOUSE OVERSIGHT 010477",
      "HOUSE OVERSIGHT 010478",
      "HOUSE OVERSIGHT 010479",
      "HOUSE OVERSIGHT 010480",
      "HOUSE OVERSIGHT 010481",
      "HOUSE OVERSIGHT 010482",
      "HOUSE OVERSIGHT 010483",
      "HOUSE OVERSIGHT 010484",
      "HOUSE OVERSIGHT 010485"
    ]
  },
  "entities": {
    "people": [
      "Jeffrey Epstein",
      "Ward",
      "Leone",
      "Jean Dubuffet",
      "Chris Bott",
      "Leslie Wexner",
      "Lynn Goldsmith",
      "Ghislaine Maxwell",
      "Tony Randall",
      "Robert Maxwell",
      "Marina Gamier",
      "Donald Trump",
      "Deborah Blohm",
      "Gwendolyn Beck",
      "Prince Andrew",
      "Alan Dershowitz",
      "Rick Friedman",
      "Joe Shildhorn",
      "Patrick McMullen",
      "Neil Rasmus",
      "Adrianna Ross",
      "Uma Sanghvi",
      "Richie Rich",
      "Larry Visoski",
      "Jae Donnelly",
      "Stephen Hawking",
      "Laura Hanifin",
      "Rob Rich",
      "Charlie Crist",
      "Scott Rothstein",
      "CarlineJean",
      "Billy Farrell",
      "Brian Vickers",
      "Jeff Moreland",
      "Michael Reiter",
      "Janet Reiter",
      "Debbie Schatz",
      "Joe Recarey",
      "Megltan McCarthy",
      "Mort Zu"
    ],
    "organizations": [
      "HOUSE OVERSIGHT",
      "Palm Beach Police Department",
      "Splash News",
      "Corbis",
      "Lafayette High School",
      "YIVO Institute",
      "Trump Model",
      "Victoria's Secret",
      "Davidoff Studios",
      "US District Southern Court of Florida",
      "Wall Street Rising",
      "Radar magazine",
      "Sipa Press",
      "Palm Beach County Sheriff's Office",
      "CDC Special Management, Palm Beach Sheriffs Office",
      "National Sex Offender Registry",
      "The Palm Beach Post",
      "ZUMAPRESS.com",
      "News of the World",
      "J. Epstein VI Foundation",
      "Center for Education and Research in Cosmology and Astrophysics (CERCA)",
      "Case Western Reserve University",
      "New York Academy of Art",
      "SocietyAllure.com",
      "Sun Sentinel",
      "Van Cleef & Arpels",
      "BFAnyc.com",
      "NASCAR",
      "Icon Sportswire",
      "AP Images",
      "YouTube",
      "Palm Beach Police Foundation",
      "Palm Beach Daily News"
    ],
    "locations": [
      "Times Square",
      "New York City",
      "England",
      "Coney Island",
      "Palm Beach",
      "358 El Brillo Way",
      "Brooklyn, New York",
      "Plaza Hotel",
      "Laura Belle club",
      "Mar-a-Lago",
      "London",
      "Zorro Ranch",
      "New Mexico",
      "Cambridge, MA",
      "Cipriani",
      "Hotel QT",
      "Fairgrounds Road",
      "West Palm Beach, Florida",
      "The Stockade",
      "Palm Beach County Stockade",
      "West Palm Beach courthouse",
      "Little Saint James island",
      "U.S. Virgin Islands",
      "Teterboro Airport",
      "New Jersey",
      "Central Park",
      "St. Thomas, USVI",
      "Herbert N. Straus Mansion",
      "East 71st Street",
      "Fort Lauderdale",
      "Churchill Downs",
      "Louisville, Kentucky"
    ],
    "dates": [
      "circa 1969",
      "1969",
      "1989",
      "November 1991",
      "April 8, 1997",
      "1995",
      "September 8, 2004",
      "2005",
      "March 15, 2005",
      "May 2005",
      "2008",
      "2006",
      "June 2008",
      "January 2015",
      "January 2016",
      "2011",
      "March 2006",
      "April 14, 2004",
      "2014",
      "April 7, 2014",
      "January 2012",
      "November 2013"
    ],
    "events": [
      "Palm Beach Police Department search warrant walk-through",
      "YIVO Institute event at the Plaza Hotel",
      "Victoria's Secret Angels party",
      "reception at Mar-a-Lago",
      "2005 Wall Street concert series",
      "launch of Radar magazine",
      "Epstein pleaded guilty to state solicitation charges",
      "Epstein's release from jail",
      "conference \"Confronting Gravity\"",
      "New York Academy of Art's Tribeca Ball",
      "141st running of the Kentucky Derby",
      "Palm Beach Police Foundation Policemen's Ball"
    ]
  },
  "themes": [
    "Jeffrey Epstein's life and associations",
    "Social events and high-profile connections",
    "Criminal investigations and legal proceedings",
    "Locations associated with Jeffrey Epstein",
    "Timeline of events"
  ],
  "confidence": 0.9,
  "notes": "The document consists of scanned pages, likely from a book's photo insert section. The text is heavily fragmented, especially on the left and right margins of each page, indicating it's an excerpt and not the full original document. The content is primarily captions for photographs, detailing people, places, and dates related to Jeffrey Epstein. Some text blocks are unreadable or nonsensical due to scanning artifacts or the nature of the original document.",
  "file_path": "TEXT\\001\\HOUSE_OVERSIGHT_010477.txt",
  "house_oversight_id": "010477",
  "processing_metadata": {
    "processed_at": "2025-11-14T01:25:26.019443Z",
    "model": "gemini-2.5-pro"
  }
}