{
  "file_name": "House_Oversight_Email_014310-014311.txt",
  "content": {
    "full_text": "From: Ens, Amanda \nSent: 11/15/2016 2:44:06 PM \nTo: jeffrey E. [jeeyacation@gmail.com]; Richard Kahn \nSubject: SPX put contingent on higher rates \nAttachments: image001.jpg; image002.jpg; image003.jpg; image005.png \nImportance: High \nNavigating post-Trump volatility \n• We are recording unprecedented divergences in falling equity vol with rising rates vol post Trump's win. Intra-\nday S&P realized vol collapsed from near 60% to below 20% in 2d [Chart 1] \n• While equities have shown less conviction over what a Trump win means (given strong sector rotation), the \nbond market has sold off with one of the largest moves in history [Chart 2 & 3] \n• Stabilizing rates volatility from here is key to markets remaining calm and while equity upside may continue, it is \nnot without higher risks \n• We like cheap optionality to hedge long-equities if rates continue to move sharply \nFor investors long equities, we look at ways to cheapen protecting from downside risks in the event of further bond \nmarket volatility catalysed by Trump policy uncertainty  \n• Buy an SPX Apr-17 95% put conditional on US 10Y CMS > 2.5% at maturity for 0.87% \nO 70% discount vs. vanilla \nO CMS ref. 2.11%, SPX ref. 2,164.2 \nCMS = constant maturity swap \nChart 1: The response in S&P 500 realized equity volatility to the US election surprise was similar to Brexit but more extreme, as the \nspike in volatility collapsed at record speed \n140% \n=•• 120% \na, 100% \n.1 \n80% - \na \n60% \n▪ 40% \n5 20% \n0% \n20% \n0% \n• \n• \n• \n• • • •• \n• • 18 \n; . . • \n•%.• • .% \n• e• j is \n• \n•••„ \n• •• \nUS Etecbon (10. & 11-Nov vol S 9-Now fol) \nBrexit (28- & 27-Jun lot vs 24-Jun %pi) \n40% 60% 80% 100% 120% \nSPX 1-day intrcityvol \nSource: BofA Merrill Lynch Global Research. Based on daily data from June 2004 to current \n140% \n160% \nChart 2: Ten-year US Treasury yields see a near record spike after Chart 3: Long Bond futures prices down near record amount \nthe US election (-5%) in the four days since the election \nHOUSE OVERSIGHT 014310 \n24% \n19% \n14% \n9% \n4% \nI \" \n8 —------ \ncn (y) \nco \n0 \nte) \n.6, \nco \nLa. \nes.1 \n6 \nFs.; \n6. \n8 \nco \ngg \n(r& \ncr) o \n70 \t15% \n60 \n50 \t10% \n40 \nII \t30 \t5% \n20  10 \t0% \n-5% \nL.r2 \t:7-\t0 \n-8  (.3 \t8  - \t•10%  1980 \t1984 \t1988 1992 \t1996 \t2000 \t2004 \t2008 \t2012 \t2016 \n• Largest 4-clav %changes in 10yr UST yeelcIs since 1962 \nChange rneasixed n bps (ngtt) \nSource BofA Merrill Lynch Global Research. Based on daily data since 1962. \nAmanda Ens \nDirector \nBank of America Merrill Lynch \nMerrill Lynch, Pierce, Fenner & Smith Incorporated \nOne Bryant Park, 5th Floor, New York, NY 10036 \nThe power of global connections' \nBankof America \nMerrill Lynch \n— 4-day rehrn of a 30fr UST futures mestrnent \n14-Na -16 \nSource BofA Merrill Lynch Global Research \nThis message, and any attachments, is for the intended recipient(s) only, may contain information that is \nprivileged, confidential and/or proprietary and subject to important terms and conditions available at \nhttp://www.bankofamerica.com/emaildisclaimer. If you are not the intended recipient, please delete this \nmessage. \nHOUSE OVERSIGHT 014311 \n",
    "sections": [
      {
        "section_index": 0,
        "section_type": "email_header",
        "text": "From: Ens, Amanda \nSent: 11/15/2016 2:44:06 PM \nTo: jeffrey E. [jeeyacation@gmail.com]; Richard Kahn \nSubject: SPX put contingent on higher rates \nAttachments: image001.jpg; image002.jpg; image003.jpg; image005.png \nImportance: High"
      },
      {
        "section_index": 1,
        "section_type": "header",
        "text": "Navigating post-Trump volatility"
      },
      {
        "section_index": 2,
        "section_type": "list",
        "text": "• We are recording unprecedented divergences in falling equity vol with rising rates vol post Trump's win. Intra-\nday S&P realized vol collapsed from near 60% to below 20% in 2d [Chart 1] \n• While equities have shown less conviction over what a Trump win means (given strong sector rotation), the \nbond market has sold off with one of the largest moves in history [Chart 2 & 3] \n• Stabilizing rates volatility from here is key to markets remaining calm and while equity upside may continue, it is \nnot without higher risks \n• We like cheap optionality to hedge long-equities if rates continue to move sharply"
      },
      {
        "section_index": 3,
        "section_type": "paragraph",
        "text": "For investors long equities, we look at ways to cheapen protecting from downside risks in the event of further bond \nmarket volatility catalysed by Trump policy uncertainty"
      },
      {
        "section_index": 4,
        "section_type": "list",
        "text": "• Buy an SPX Apr-17 95% put conditional on US 10Y CMS > 2.5% at maturity for 0.87% \nO 70% discount vs. vanilla \nO CMS ref. 2.11%, SPX ref. 2,164.2 \nCMS = constant maturity swap"
      },
      {
        "section_index": 5,
        "section_type": "chart_description",
        "text": "Chart 1: The response in S&P 500 realized equity volatility to the US election surprise was similar to Brexit but more extreme, as the \nspike in volatility collapsed at record speed"
      },
      {
        "section_index": 6,
        "section_type": "chart_data",
        "text": "140% \n=•• 120% \na, 100% \n.1 \n80% - \na \n60% \n▪ 40% \n5 20% \n0% \n20% \n0% \n• \n• \n• \n• • • •• \n• • 18 \n; . . • \n•%.• • .% \n• e• j is \n• \n•••„ \n• •• \nUS Etecbon (10. & 11-Nov vol S 9-Now fol) \nBrexit (28- & 27-Jun lot vs 24-Jun %pi) \n40% 60% 80% 100% 120% \nSPX 1-day intrcityvol \nSource: BofA Merrill Lynch Global Research. Based on daily data from June 2004 to current"
      },
      {
        "section_index": 7,
        "section_type": "chart_description",
        "text": "Chart 2: Ten-year US Treasury yields see a near record spike after Chart 3: Long Bond futures prices down near record amount \nthe US election (-5%) in the four days since the election"
      },
      {
        "section_index": 8,
        "section_type": "footer",
        "text": "HOUSE OVERSIGHT 014310"
      },
      {
        "section_index": 9,
        "section_type": "chart_data",
        "text": "24% \n19% \n14% \n9% \n4% \nI \" \n8 —------ \ncn (y) \nco \n0 \nte) \n.6, \nco \nLa. \nes.1 \n6 \nFs.; \n6. \n8 \nco \ngg \n(r& \ncr) o \n70 \t15% \n60 \n50 \t10% \n40 \nII \t30 \t5% \n20  10 \t0% \n-5% \nL.r2 \t:7-\t0 \n-8  (.3 \t8  - \t•10%  1980 \t1984 \t1988 1992 \t1996 \t2000 \t2004 \t2008 \t2012 \t2016 \n• Largest 4-clav %changes in 10yr UST yeelcIs since 1962 \nChange rneasixed n bps (ngtt) \nSource BofA Merrill Lynch Global Research. Based on daily data since 1962."
      },
      {
        "section_index": 10,
        "section_type": "chart_data",
        "text": "— 4-day rehrn of a 30fr UST futures mestrnent \n14-Na -16 \nSource BofA Merrill Lynch Global Research"
      },
      {
        "section_index": 11,
        "section_type": "signature",
        "text": "Amanda Ens \nDirector \nBank of America Merrill Lynch \nMerrill Lynch, Pierce, Fenner & Smith Incorporated \nOne Bryant Park, 5th Floor, New York, NY 10036 \nThe power of global connections' \nBankof America \nMerrill Lynch"
      },
      {
        "section_index": 12,
        "section_type": "disclaimer",
        "text": "This message, and any attachments, is for the intended recipient(s) only, may contain information that is \nprivileged, confidential and/or proprietary and subject to important terms and conditions available at \nhttp://www.bankofamerica.com/emaildisclaimer. If you are not the intended recipient, please delete this \nmessage."
      },
      {
        "section_index": 13,
        "section_type": "footer",
        "text": "HOUSE OVERSIGHT 014311"
      }
    ]
  },
  "metadata": {
    "document_type": "Email",
    "participants": [
      "Ens, Amanda",
      "jeffrey E.",
      "Richard Kahn"
    ],
    "date_range": {
      "earliest": "2016-11-15",
      "latest": "2016-11-15"
    },
    "file_references": [
      "HOUSE OVERSIGHT 014310",
      "HOUSE OVERSIGHT 014311"
    ]
  },
  "entities": {
    "people": [
      "Ens, Amanda",
      "jeffrey E.",
      "Richard Kahn",
      "Trump"
    ],
    "organizations": [
      "Bank of America Merrill Lynch",
      "BofA Merrill Lynch Global Research",
      "Merrill Lynch, Pierce, Fenner & Smith Incorporated",
      "Bank of America",
      "Merrill Lynch",
      "US Treasury",
      "House Oversight Committee"
    ],
    "locations": [
      "One Bryant Park, 5th Floor, New York, NY 10036",
      "New York, NY"
    ],
    "dates": [
      "11/15/2016",
      "Apr-17",
      "June 2004",
      "10-Nov",
      "11-Nov",
      "9-Nov",
      "28-Jun",
      "27-Jun",
      "24-Jun",
      "1962",
      "1980",
      "1984",
      "1988",
      "1992",
      "1996",
      "2000",
      "2004",
      "2008",
      "2012",
      "2016",
      "14-Na -16"
    ],
    "events": [
      "Trump's win",
      "US election",
      "Brexit"
    ]
  },
  "themes": [
    "Financial Market Analysis",
    "Post-Election Market Volatility",
    "Investment Strategy",
    "Equity Hedging",
    "Interest Rate Volatility",
    "Derivatives Trading"
  ],
  "confidence": 0.95,
  "notes": "The document is an email from a Bank of America Merrill Lynch director discussing market volatility following the 2016 US presidential election. It includes an investment recommendation for an SPX put option. The text contains several embedded charts which are represented by their textual descriptions and labels. Some text within the chart images is garbled or contains typos (e.g., 'Etecbon', 'intrcityvol', 'yeelcIs', 'rneasixed', 'rehrn', 'mestrnent'). The document has Bates numbers 'HOUSE OVERSIGHT 014310' and 'HOUSE OVERSIGHT 014311' at the bottom of the pages.",
  "file_path": "TEXT\\001\\HOUSE_OVERSIGHT_014310.txt",
  "house_oversight_id": "014310",
  "processing_metadata": {
    "processed_at": "2025-11-14T03:02:26.892024Z",
    "model": "gemini-2.5-pro"
  }
}