{
  "file_name": "HouseOversight_012707-012710_Letter_and_Contact_List.txt",
  "content": {
    "full_text": "I WEST PALM BEACH OFFICE: \n2139 PALM BEACH LAKES BLVD. \nWEST PALM BEACH, FLORIDA 33409 \nRO. BOX 3626 \nWEST PALM BEACH, FLORIDA 33402 \n(561) 686-6300 \n1-800-780-8607 \n1-800-220-7006 Spanish \nATTORNEYS AT LAW: \nROSALYN SIA BAKER-BARNES \n'F. GREGORY BARNHART \nT. HARDEE BASS, III \nLAURIE J. BRIGGS \nBRIAN R. DENNEY \n'EARL L. DENNEY, JR.5 \nBRENDA S. FULMER \nJAMES W. GUSTAFSON, JR. \nJACK R HILL \nDAVID K. KELLEY, JR. \nWILLIAM B. KING7 \n'DARRYL L. LEWIS' \n*WILLIAM A. NORTON \nPATRICK E. QUINLAN' \nEDWARD V. RICCI \nDAVID J. SALES' \n*JOHN SCAROLA \nCHRISTIAN D. SEARCY \n*JOHN A. SHIPLEY III \nCHRISTOPHER K. SPEED 55 \nBRIAN P. SULLIVAN 345 \nKAREN E. TERRY \nT. CALVIN WARRINER III \nSHAREHOLDERS \n*BOARD CERTIFIED \nAPO ADMITTED \nKENTUCKY \nMAINE \n3 MARYLAND \n4 MASSACHUSETTS \n5 MISSISSIPPI \n6 NEW HAMPSHIRE \n7 NEW JERSEY \nVIRGINIA \nWASHINGTON DC \nPARALEGALS: \nVIVIAN AYAN-TEJEDA \nALYSSA A. DIEDWARDO \nRANDY M. DUFRESNE \nDAVID W. GILMORE \nJOHN C. HOPKINS \nDEBORAH M. KNAPP \nVINCENT L LEONARD, JR. \nJAMES PETER LOVE \nCHRISTOPHER J. PILATO \nROBERT W. PITCHER \nMARK P. PONCY \nKATHLEEN SIMON \nSTEVE M. SMITH \nBONNIE S. STARK \nWALTER A. STEIN \nSEARCY \nDENNEY \nSCAROLA \nBARN HART \ne-SH1PLEYpA  \nd m() \nVIA EMAIL AND U.S. MAIL \nMarch 22, 2011 \nRobert B. Carney, Special Master \n2281 Saratoga Lane \nWest Palm Beach, FL 33409 \nOTALLAHASSEE OFFICE: \nTHE TOWLE HOUSE \n517 NORTH CALHOUN STREET \nTALLAHASSEE, FL 32301-1231 \nRO. BOX 1230 \nTALLAHASSEE, FLORIDA 32302 \nRe: Edwards adv. Epstein \nOur File No.: 291874 \nDear Judge Carney: \nAttached please find the Master Contact List pursuant to your Interim Report in this \nmatter. \nSincerely, \nDictated But Not Signed By \nJack Scarola To Expedite Delivery \nJACK SCAROLA \nJS/mep \nEnc. \ncc: Bradley J. Edwards, Esq. \nJoseph L. Ackerman, Esq. \nChristopher Knight, Esq. \n(850) 224-7600 \n1-888-549-7011 \nWWW.SEARCYLAW.COM \nHOUSE OVERSIGHT 012707 \nMASTER CONTACT LIST REGARDING Privilege Log — Dated 2-23-2011 \nFarmer.laffe, Weissing, Edwards, Fistos & Lehrman  \nCONTACT NAME \tIDENTITY \nAdam Horowitz \tCounsel for other Epstein Victims \nAdam Steinberg \tAttorney RRA \nAlan Garten \tDonald Trump's attorney \nAmy Eden i \tRobert Josefsberg's daughter \nAmy Swan \tExpert in Epstein Case \nAnthony P \tRRA CLIENT \nAttorneys at RRA \nBarry Stone \tAttorney RRA \nBert Patton \tLegal Assistant to Robert Josefsberg \nBeth Williamson \tParalegal RRA \nBradley Edwards \tAttorney RRA \nCara Holmes \tAttorney RRA \nCarl Linder \tAttorney RRA \nCarla Martinez \tLaw Clerk at RRA \nCarolyn \t(Legal Asst. to Jay Howell, Co-Counsel) \nCarolyn Edwards \t(Legal Asst. to Jay Howell, Co-Counsel) \nConfidential Source \nChristina Fitch \tStaff RRA \nDenis Kleinfeld \tAttorney RRA \nD.F. \tClient (Epstein Case) \nDr. Lee \tExpert (Epstein Case) \nEarleen Cote \tAttorney \nElizabeth Kim \tParalegal RRA \nElizabeth Villar \tLegal Assistant RRA \nGary Farmer \tAttorney RRA \nGrant Smith \tAttorney RRA \nIleana Yarzabal \tPrior Paralegal to Robert Josefsberg \nInvestigators \tInvestigators RRA \nJack Hill \tCounsel for other Epstein Victims \nJack Scarola \tCounsel for other Epstein Victims \nJacquie Johnson \tParalegal RRA \nJessica Caldwell \tAttorney Critton's Assistant \nJosh Roberts \tAttorney \nJonathan Birkman \tAttorney RRA \nHOUSE OVERSIGHT 012708 \nMASTER CONTACT LIST REGARDING Privilege Log — Dated 2-23-2011 \nFarmer, Jaffe, Weissing, Edwards, Fistos & Lehrman  \nKatherine Ezell \tCounsel for other Epstein Victims \nKikka Claudio \tAssistant to Attorney Jack Hill \nKendall Coffey \tSpecial Counsel to RRA on Epstein Case \nKen Jenne \tInvestigators RRA \nLisa Rivera \tLegal Assistant to Adam Horowitz \nLitigation Team \tRRA attorneys and staff \nMarc Nurik \tAttorney RRA \nMargaret Berk \tLegal Assistant to Spencer Kuvin \nMaribel Matiska \tRRA Paralegal \nMark Fistos \tAttorney RRA \nMercedes Estrada \tKatherine Ezell's Assistant \nMG \tClient (Epstein Case) \nMichael Wheeler \tAttorney RRA \nMike Fisten \tInvestigators RRA \nN.R. \tClient communication \nNora Batian \tRRA Staff \nPasqual \"Pat\" Diaz \tInvestigators RRA \nPat Roberts \tInvestigators RRA \nPaul Cassel \tCo-Counsel on Epstein Case \nPhaedra Xanthos \tForensic Accountant \nPriscila Nascimento \tStaff RRA \nRichard Willits \tAttorney \nRichard Wolfe \tAttorney RRA \nRobert Buschel \tAttorney RRA \nRobert C. Josefsbergs \tCounsel for other Epstein Victims \nRobin T. Kempner \tRRA Staff \nRonald Wise \tForensics (Epstein Case) \nRRA Personnel \tRRA \nRussell Adler \tAttorney RRA \nScott Goldstein \tAttorney RRA \nScott Rothstein \tAttorney RRA \nSeth Lehrman \tAttorney RRA \nShawn Gilbert \tPrior Legal Assistant to Brad Edwards \nSid Garcia \tCounsel for other Epstein Victims \nSpencer Kuvin \tCounsel for other Epstein Victims \nSteven Jaffe \tAttorney RRA \nStuart Mermelstein \tCounsel for other Epstein Victims \nHOUSE OVERSIGHT 012709 \nMASTER CONTACT LIST REGARDING Privilege Log — Dated 2-23-2011 \nFarmer, Jaffe, Weissing, Edwards, Fistos & Lehrman  \nSusan K. Stirling \tRRA Staff \nTami Wolfe \tAttorney RRA \nT. Edwards \tBrad Edwards Wife \nUnknown Staff \tRRA STAFF \nWayne Black \tPrivate Investigator \nWilliam J. Berger \tAttorney RRA \nHOUSE OVERSIGHT 012710 \n",
    "sections": [
      {
        "section_index": 1,
        "section_type": "letterhead",
        "text": "I WEST PALM BEACH OFFICE: \n2139 PALM BEACH LAKES BLVD. \nWEST PALM BEACH, FLORIDA 33409 \nRO. BOX 3626 \nWEST PALM BEACH, FLORIDA 33402 \n(561) 686-6300 \n1-800-780-8607 \n1-800-220-7006 Spanish \nATTORNEYS AT LAW: \nROSALYN SIA BAKER-BARNES \n'F. GREGORY BARNHART \nT. HARDEE BASS, III \nLAURIE J. BRIGGS \nBRIAN R. DENNEY \n'EARL L. DENNEY, JR.5 \nBRENDA S. FULMER \nJAMES W. GUSTAFSON, JR. \nJACK R HILL \nDAVID K. KELLEY, JR. \nWILLIAM B. KING7 \n'DARRYL L. LEWIS' \n*WILLIAM A. NORTON \nPATRICK E. QUINLAN' \nEDWARD V. RICCI \nDAVID J. SALES' \n*JOHN SCAROLA \nCHRISTIAN D. SEARCY \n*JOHN A. SHIPLEY III \nCHRISTOPHER K. SPEED 55 \nBRIAN P. SULLIVAN 345 \nKAREN E. TERRY \nT. CALVIN WARRINER III \nSHAREHOLDERS \n*BOARD CERTIFIED \nAPO ADMITTED \nKENTUCKY \nMAINE \n3 MARYLAND \n4 MASSACHUSETTS \n5 MISSISSIPPI \n6 NEW HAMPSHIRE \n7 NEW JERSEY \nVIRGINIA \nWASHINGTON DC \nPARALEGALS: \nVIVIAN AYAN-TEJEDA \nALYSSA A. DIEDWARDO \nRANDY M. DUFRESNE \nDAVID W. GILMORE \nJOHN C. HOPKINS \nDEBORAH M. KNAPP \nVINCENT L LEONARD, JR. \nJAMES PETER LOVE \nCHRISTOPHER J. PILATO \nROBERT W. PITCHER \nMARK P. PONCY \nKATHLEEN SIMON \nSTEVE M. SMITH \nBONNIE S. STARK \nWALTER A. STEIN \nSEARCY \nDENNEY \nSCAROLA \nBARN HART \ne-SH1PLEYpA  \nd m() \nVIA EMAIL AND U.S. MAIL"
      },
      {
        "section_index": 2,
        "section_type": "letterhead",
        "text": "OTALLAHASSEE OFFICE: \nTHE TOWLE HOUSE \n517 NORTH CALHOUN STREET \nTALLAHASSEE, FL 32301-1231 \nRO. BOX 1230 \nTALLAHASSEE, FLORIDA 32302 \n(850) 224-7600 \n1-888-549-7011 \nWWW.SEARCYLAW.COM"
      },
      {
        "section_index": 3,
        "section_type": "letter",
        "text": "March 22, 2011 \nRobert B. Carney, Special Master \n2281 Saratoga Lane \nWest Palm Beach, FL 33409 \n\nRe: Edwards adv. Epstein \nOur File No.: 291874 \n\nDear Judge Carney: \n\nAttached please find the Master Contact List pursuant to your Interim Report in this \nmatter. \n\nSincerely, \n\nDictated But Not Signed By \nJack Scarola To Expedite Delivery \nJACK SCAROLA \n\nJS/mep \nEnc. \n\ncc: Bradley J. Edwards, Esq. \nJoseph L. Ackerman, Esq. \nChristopher Knight, Esq."
      },
      {
        "section_index": 4,
        "section_type": "footer",
        "text": "HOUSE OVERSIGHT 012707"
      },
      {
        "section_index": 5,
        "section_type": "list",
        "text": "MASTER CONTACT LIST REGARDING Privilege Log — Dated 2-23-2011 \nFarmer.laffe, Weissing, Edwards, Fistos & Lehrman  \nCONTACT NAME \tIDENTITY \nAdam Horowitz \tCounsel for other Epstein Victims \nAdam Steinberg \tAttorney RRA \nAlan Garten \tDonald Trump's attorney \nAmy Eden i \tRobert Josefsberg's daughter \nAmy Swan \tExpert in Epstein Case \nAnthony P \tRRA CLIENT \nAttorneys at RRA \nBarry Stone \tAttorney RRA \nBert Patton \tLegal Assistant to Robert Josefsberg \nBeth Williamson \tParalegal RRA \nBradley Edwards \tAttorney RRA \nCara Holmes \tAttorney RRA \nCarl Linder \tAttorney RRA \nCarla Martinez \tLaw Clerk at RRA \nCarolyn \t(Legal Asst. to Jay Howell, Co-Counsel) \nCarolyn Edwards \t(Legal Asst. to Jay Howell, Co-Counsel) \nConfidential Source \nChristina Fitch \tStaff RRA \nDenis Kleinfeld \tAttorney RRA \nD.F. \tClient (Epstein Case) \nDr. Lee \tExpert (Epstein Case) \nEarleen Cote \tAttorney \nElizabeth Kim \tParalegal RRA \nElizabeth Villar \tLegal Assistant RRA \nGary Farmer \tAttorney RRA \nGrant Smith \tAttorney RRA \nIleana Yarzabal \tPrior Paralegal to Robert Josefsberg \nInvestigators \tInvestigators RRA \nJack Hill \tCounsel for other Epstein Victims \nJack Scarola \tCounsel for other Epstein Victims \nJacquie Johnson \tParalegal RRA \nJessica Caldwell \tAttorney Critton's Assistant \nJosh Roberts \tAttorney \nJonathan Birkman \tAttorney RRA"
      },
      {
        "section_index": 6,
        "section_type": "footer",
        "text": "HOUSE OVERSIGHT 012708"
      },
      {
        "section_index": 7,
        "section_type": "list",
        "text": "MASTER CONTACT LIST REGARDING Privilege Log — Dated 2-23-2011 \nFarmer, Jaffe, Weissing, Edwards, Fistos & Lehrman  \nKatherine Ezell \tCounsel for other Epstein Victims \nKikka Claudio \tAssistant to Attorney Jack Hill \nKendall Coffey \tSpecial Counsel to RRA on Epstein Case \nKen Jenne \tInvestigators RRA \nLisa Rivera \tLegal Assistant to Adam Horowitz \nLitigation Team \tRRA attorneys and staff \nMarc Nurik \tAttorney RRA \nMargaret Berk \tLegal Assistant to Spencer Kuvin \nMaribel Matiska \tRRA Paralegal \nMark Fistos \tAttorney RRA \nMercedes Estrada \tKatherine Ezell's Assistant \nMG \tClient (Epstein Case) \nMichael Wheeler \tAttorney RRA \nMike Fisten \tInvestigators RRA \nN.R. \tClient communication \nNora Batian \tRRA Staff \nPasqual \"Pat\" Diaz \tInvestigators RRA \nPat Roberts \tInvestigators RRA \nPaul Cassel \tCo-Counsel on Epstein Case \nPhaedra Xanthos \tForensic Accountant \nPriscila Nascimento \tStaff RRA \nRichard Willits \tAttorney \nRichard Wolfe \tAttorney RRA \nRobert Buschel \tAttorney RRA \nRobert C. Josefsbergs \tCounsel for other Epstein Victims \nRobin T. Kempner \tRRA Staff \nRonald Wise \tForensics (Epstein Case) \nRRA Personnel \tRRA \nRussell Adler \tAttorney RRA \nScott Goldstein \tAttorney RRA \nScott Rothstein \tAttorney RRA \nSeth Lehrman \tAttorney RRA \nShawn Gilbert \tPrior Legal Assistant to Brad Edwards \nSid Garcia \tCounsel for other Epstein Victims \nSpencer Kuvin \tCounsel for other Epstein Victims \nSteven Jaffe \tAttorney RRA \nStuart Mermelstein \tCounsel for other Epstein Victims"
      },
      {
        "section_index": 8,
        "section_type": "footer",
        "text": "HOUSE OVERSIGHT 012709"
      },
      {
        "section_index": 9,
        "section_type": "list",
        "text": "MASTER CONTACT LIST REGARDING Privilege Log — Dated 2-23-2011 \nFarmer, Jaffe, Weissing, Edwards, Fistos & Lehrman  \nSusan K. Stirling \tRRA Staff \nTami Wolfe \tAttorney RRA \nT. Edwards \tBrad Edwards Wife \nUnknown Staff \tRRA STAFF \nWayne Black \tPrivate Investigator \nWilliam J. Berger \tAttorney RRA"
      },
      {
        "section_index": 10,
        "section_type": "footer",
        "text": "HOUSE OVERSIGHT 012710"
      }
    ]
  },
  "metadata": {
    "document_type": "Business Letter with Attachment",
    "participants": [
      "Jack Scarola",
      "Robert B. Carney",
      "Bradley J. Edwards",
      "Joseph L. Ackerman",
      "Christopher Knight"
    ],
    "date_range": {
      "earliest": "2011-02-23",
      "latest": "2011-03-22"
    },
    "file_references": [
      "291874",
      "HOUSE OVERSIGHT 012707",
      "HOUSE OVERSIGHT 012708",
      "HOUSE OVERSIGHT 012709",
      "HOUSE OVERSIGHT 012710"
    ]
  },
  "entities": {
    "people": [
      "ROSALYN SIA BAKER-BARNES",
      "F. GREGORY BARNHART",
      "T. HARDEE BASS, III",
      "LAURIE J. BRIGGS",
      "BRIAN R. DENNEY",
      "EARL L. DENNEY, JR.",
      "BRENDA S. FULMER",
      "JAMES W. GUSTAFSON, JR.",
      "JACK R HILL",
      "DAVID K. KELLEY, JR.",
      "WILLIAM B. KING",
      "DARRYL L. LEWIS",
      "WILLIAM A. NORTON",
      "PATRICK E. QUINLAN",
      "EDWARD V. RICCI",
      "DAVID J. SALES",
      "JOHN SCAROLA",
      "CHRISTIAN D. SEARCY",
      "JOHN A. SHIPLEY III",
      "CHRISTOPHER K. SPEED",
      "BRIAN P. SULLIVAN",
      "KAREN E. TERRY",
      "T. CALVIN WARRINER III",
      "VIVIAN AYAN-TEJEDA",
      "ALYSSA A. DIEDWARDO",
      "RANDY M. DUFRESNE",
      "DAVID W. GILMORE",
      "JOHN C. HOPKINS",
      "DEBORAH M. KNAPP",
      "VINCENT L LEONARD, JR.",
      "JAMES PETER LOVE",
      "CHRISTOPHER J. PILATO",
      "ROBERT W. PITCHER",
      "MARK P. PONCY",
      "KATHLEEN SIMON",
      "STEVE M. SMITH",
      "BONNIE S. STARK",
      "WALTER A. STEIN",
      "Robert B. Carney",
      "Jack Scarola",
      "Bradley J. Edwards",
      "Joseph L. Ackerman",
      "Christopher Knight",
      "Epstein",
      "Adam Horowitz",
      "Adam Steinberg",
      "Alan Garten",
      "Donald Trump",
      "Amy Eden",
      "Robert Josefsberg",
      "Amy Swan",
      "Anthony P",
      "Barry Stone",
      "Bert Patton",
      "Beth Williamson",
      "Cara Holmes",
      "Carl Linder",
      "Carla Martinez",
      "Carolyn",
      "Jay Howell",
      "Carolyn Edwards",
      "Christina Fitch",
      "Denis Kleinfeld",
      "D.F.",
      "Dr. Lee",
      "Earleen Cote",
      "Elizabeth Kim",
      "Elizabeth Villar",
      "Gary Farmer",
      "Grant Smith",
      "Ileana Yarzabal",
      "Jack Hill",
      "Jacquie Johnson",
      "Jessica Caldwell",
      "Attorney Critton",
      "Josh Roberts",
      "Jonathan Birkman",
      "Katherine Ezell",
      "Kikka Claudio",
      "Kendall Coffey",
      "Ken Jenne",
      "Lisa Rivera",
      "Marc Nurik",
      "Margaret Berk",
      "Spencer Kuvin",
      "Maribel Matiska",
      "Mark Fistos",
      "Mercedes Estrada",
      "MG",
      "Michael Wheeler",
      "Mike Fisten",
      "N.R.",
      "Nora Batian",
      "Pasqual \"Pat\" Diaz",
      "Pat Roberts",
      "Paul Cassel",
      "Phaedra Xanthos",
      "Priscila Nascimento",
      "Richard Willits",
      "Richard Wolfe",
      "Robert Buschel",
      "Robert C. Josefsbergs",
      "Robin T. Kempner",
      "Ronald Wise",
      "Russell Adler",
      "Scott Goldstein",
      "Scott Rothstein",
      "Seth Lehrman",
      "Shawn Gilbert",
      "Brad Edwards",
      "Sid Garcia",
      "Steven Jaffe",
      "Stuart Mermelstein",
      "Susan K. Stirling",
      "Tami Wolfe",
      "T. Edwards",
      "Wayne Black",
      "William J. Berger"
    ],
    "organizations": [
      "SEARCY DENNEY SCAROLA BARNHART & SHIPLEY, P.A.",
      "HOUSE OVERSIGHT",
      "Farmer, Jaffe, Weissing, Edwards, Fistos & Lehrman",
      "RRA"
    ],
    "locations": [
      "WEST PALM BEACH, FLORIDA 33409",
      "WEST PALM BEACH, FLORIDA 33402",
      "2139 PALM BEACH LAKES BLVD.",
      "West Palm Beach, FL 33409",
      "2281 Saratoga Lane",
      "TALLAHASSEE, FL 32301-1231",
      "517 NORTH CALHOUN STREET",
      "TALLAHASSEE, FLORIDA 32302",
      "KENTUCKY",
      "MAINE",
      "MARYLAND",
      "MASSACHUSETTS",
      "MISSISSIPPI",
      "NEW HAMPSHIRE",
      "NEW JERSEY",
      "VIRGINIA",
      "WASHINGTON DC"
    ],
    "dates": [
      "March 22, 2011",
      "2-23-2011"
    ],
    "events": [
      "Edwards adv. Epstein case",
      "Submission of Master Contact List",
      "Issuance of Interim Report by Special Master"
    ]
  },
  "themes": [
    "Legal Correspondence",
    "Litigation Support",
    "Contact and Personnel Listing",
    "Privilege Log",
    "Epstein Case"
  ],
  "confidence": 1.0,
  "notes": "The document is a cover letter from the law firm Searcy Denney Scarola Barnhart & Shipley, P.A. to a Special Master, Robert B. Carney, transmitting a 'Master Contact List' related to the 'Edwards adv. Epstein' case. The contact list itself appears to be from another firm, 'Farmer, Jaffe, Weissing, Edwards, Fistos & Lehrman', and is associated with a privilege log. The list contains names and roles of various individuals involved in the case, including attorneys, paralegals, experts, investigators, and clients. The document contains Bates numbers (HOUSE OVERSIGHT 012707-012710), indicating it is part of a larger production of documents for a House Oversight Committee investigation.",
  "file_path": "TEXT\\001\\HOUSE_OVERSIGHT_012707.txt",
  "house_oversight_id": "012707",
  "processing_metadata": {
    "processed_at": "2025-11-14T02:19:08.404232Z",
    "model": "gemini-2.5-pro"
  }
}