{
  "file_name": "House Oversight Committee Documentation Email Chain",
  "content": {
    "full_text": "From: Ens, Amanda_____________________________ \nSent: 12/9/2016 4:03:45 PM \nTo: jeffrey E. [jeeyacation@gmail.com]; Richard Kah ___________________________________ \nSubject: RE: Financials: buy XLF call spreads \nAttachments: image001.png \nImportance: High \nThank you Jeffrey. Notional is $14,285,000. I'll be back with final trade details. \nFrom: Jeffrey E. [mailto:jeevacation@gmail.com] \nSent: Friday, December 09, 2016 10:56 AM \nTo: Ens, Amanda; Richard Kahn \nSubject: Re: Financials: buy XLF call spreads \nlets try, 250k premium \nOn Fri, Dec 9, 2016 at 11:46 AM, Ens, Amanda wrote: \nWe continue to see further upside in financials. \n• Erika Najarian, BAML financials research analyst, just returned from a marketing trip. Bottom line: North American \ninvestors are very bullish the banks (long only AND hedge funds AND macro funds), but then conclude \"I don't own \nenough\". Note that high touch flows have slowed down significantly since Thanksgiving and where the buying has been \nconcentrated in XLF (every client sector we have has been a better buyer of XLF). \n• Client focus: \n1) Regulation: Excitement, with the base case that it's not getting worse. \n2) Sentiment on rates: Cautiously bullish \n3) Sentiment on growth: Also bullish \n4) Sentiment on corporate tax rate cuts: buyside more bullish than sellside. In 1986, bank stocks exploded upward \n(outperforming the S&P) after Reagan's tax reform bill passed the Senate; and 2) in 2003, the last time we saw personal \ntax cuts, loan growth industry wide accelerated in 2003 and 2004. \n• Biggest Pushback on owning sector at current levels: Too far too fast: BKX +18.00% post election: Valuation coming \ninto question and 04 has typically been a seasonally weak qtr. Bulls defend valuation on '18ests with potential upside to \n2018 [PS from —25-40% and stocks still cheap vs. discretionary. \n• Price action and sentiment keeps us constructive, we like the long and would expect US financials to benefit from \nany beta chase into year end. \n• How to play it? We still like \"appearing\" call spreads on XLF \no Buy a 6 month 105% call with a short 110% call that knock in if XLF trades above 115% during the life of the trade \nfor 1.75% premium cost \n• Gross max payoff if knock-in is triggered: 2.8x (5.0%/1.75%) \n• Gross max payoff if knock-in is not triggered: 5.6x (9.9%/1.75%) — you have upside up to 114.9% \nHOUSE OVERSIGHT 011280 \nRegards, \nAmanda \nAmanda Ens \nDirector Global Equities \nBank of America Merrill Lynch \nMerrill Lynch, Pierce, Fenner & Smith Incorporated \nOne Bryant Park 15th Floor New York, NY 10036 \nPhone Mobile \nFrom: Ens, Amanda \nSent: Tuesday, November 22, 2016 2:15 PM \nTo: 'jeffrey E.'; Rich Kahn \nSubject: Financials: buy XLF call spreads \nUnderweight positioning, buybacks resuming, positive momentum and strong fundamentals all indicate that there is still \nfurther upside potential in financials (more details below). Our financials sector specialist thinks XLF could have another \n20-25% upside given the many levers to the Trump Trade: less regulation, higher interest rates, higher vol, economic \ngrowth, loan growth, etc. The asset sensitive regional banks are more of a pure play on a rates move but we view the \nlarger cap banks as having multi-pronged upside given the aforementioned points. \nThat said, given the velocity and magnitude of the recent move and uncertainty around the impact and timing of \nTrump's policies, we believe options offer better risk-reward than being outright long financials stocks here. With flat \ncall skew, \"appearing\" call spreads with upside knock-ins price well. \nBuy a 1 year XLF call spread for 2.6% premium \n• Buy a 110% call \n• Sell a 117.5% call with an at-expiry knock-in at 125% (call is not active unless XLF is 125% or higher at expiry) \no Total premium is 2.6% \no Gross max payoff if knock-in is triggered: 2.9x (7.5%/2.6%) \no Gross max payoff if knock-in is not triggered: 5.7x (14.9%/2.6%) — you have upside up to 124.9% \nPost Election Flow Skews - Buyers of Health Care (via ETFs) and Financials (mainly ETFs) \n• US Buyback Flows \n• Cons Disc, Technology and Financials are the largest 3 sectors for US buybacks (over 70% of execution). We \nare seeing a seasonal increase in buybacks as we come out of the low seasonal month of the year (October) and should \nsee increased buyback executions until year-end, another source of upside for the Cons Disc, Technology and Financials  \nsectors.  \nGlobal Positioning, Nigel Tupper, 11/14. Large long-only funds are more underweight Financials than any other \nsector and are UW this sector in all regions. \nFuture of Financials conference hosted 90 public and private companies at our Future of Financials conference. We are \nraising our price objectives across most of our names. Three primary reasons why we think there is upside remaining \nHOUSE OVERSIGHT 011281 \nafter the recent rally: 1) an improved outlook on both activity levels and interest rates, driving revenue upside; 2) \npotentially lower regulatory burden, particularly as new supervisory leadership can come with the new administration; \nand 3) relatively lighter positioning in US financials vs. other sectors. (Erika Najarian) \nTrades Gaining Momentum: Finance-Related Assets vs. S&P 500 \nIn the period since the US presidential election, the three top-performing S&P sectors and industry groups have all been \nfinance-related (Banks, Financials, Diversified Financials) \nSource: Kensho Technologies \nThe Flow Show, Michael Hartnett, 11/18. Violent rotation: record equity ETF inflow, record financials inflow, biggest \nbond outflow in 3.5 yrs, record EM debt outflow. \nRegards, \nAmanda \nAmanda Ens \nDirector 1 Global Equities \nBank of America Merrill Lynch \nMerrill Lynch, Pierce, Fenner & Smith Incorporated \nOne Bryant Park 15th Floor New York, NY 10036 \nPhone: Mobile: \nThis message, and any attachments, is for the intended recipient(s) only, may contain information that is \nprivileged, confidential and/or proprietary and subject to important terms and conditions available at \nHOUSE OVERSIGHT 011282 \nhttp://www.bankofamerica.com/emaildisclaimer. If you are not the intended recipient, please delete this \nmessage. \nplease note \nThe information contained in this communication is \nconfidential, may be attorney-client privileged, may \nconstitute inside information, and is intended only for \nthe use of the addressee. It is the property of \nJEE \nUnauthorized use, disclosure or copying of this \ncommunication or any part thereof is strictly prohibited \nand may be unlawful. If you have received this \ncommunication in error, please notify us immediately by \nreturn e-mail or by e-mail to jeevacation@gmail.com, and \ndestroy this communication and all copies thereof, \nincluding all attachments. copyright -all rights reserved \nThis message, and any attachments, is for the intended recipient(s) only, may contain information that is \nprivileged, confidential and/or proprietary and subject to important terms and conditions available at \nhttp://www.bankofamerica.com/emaildisclaimer. If you are not the intended recipient, please delete this \nmessage. \nHOUSE OVERSIGHT 011283 \n",
    "sections": [
      {
        "section_index": 0,
        "section_type": "email_header",
        "text": "From: Ens, Amanda_____________________________ \nSent: 12/9/2016 4:03:45 PM \nTo: jeffrey E. [jeeyacation@gmail.com]; Richard Kah ___________________________________ \nSubject: RE: Financials: buy XLF call spreads \nAttachments: image001.png \nImportance: High"
      },
      {
        "section_index": 1,
        "section_type": "paragraph",
        "text": "Thank you Jeffrey. Notional is $14,285,000. I'll be back with final trade details."
      },
      {
        "section_index": 2,
        "section_type": "email_header",
        "text": "From: Jeffrey E. [mailto:jeevacation@gmail.com] \nSent: Friday, December 09, 2016 10:56 AM \nTo: Ens, Amanda; Richard Kahn \nSubject: Re: Financials: buy XLF call spreads"
      },
      {
        "section_index": 3,
        "section_type": "paragraph",
        "text": "lets try, 250k premium"
      },
      {
        "section_index": 4,
        "section_type": "quoted_email_header",
        "text": "On Fri, Dec 9, 2016 at 11:46 AM, Ens, Amanda wrote:"
      },
      {
        "section_index": 5,
        "section_type": "paragraph",
        "text": "We continue to see further upside in financials."
      },
      {
        "section_index": 6,
        "section_type": "list",
        "text": "• Erika Najarian, BAML financials research analyst, just returned from a marketing trip. Bottom line: North American \ninvestors are very bullish the banks (long only AND hedge funds AND macro funds), but then conclude \"I don't own \nenough\". Note that high touch flows have slowed down significantly since Thanksgiving and where the buying has been \nconcentrated in XLF (every client sector we have has been a better buyer of XLF). \n• Client focus: \n1) Regulation: Excitement, with the base case that it's not getting worse. \n2) Sentiment on rates: Cautiously bullish \n3) Sentiment on growth: Also bullish \n4) Sentiment on corporate tax rate cuts: buyside more bullish than sellside. In 1986, bank stocks exploded upward \n(outperforming the S&P) after Reagan's tax reform bill passed the Senate; and 2) in 2003, the last time we saw personal \ntax cuts, loan growth industry wide accelerated in 2003 and 2004. \n• Biggest Pushback on owning sector at current levels: Too far too fast: BKX +18.00% post election: Valuation coming \ninto question and 04 has typically been a seasonally weak qtr. Bulls defend valuation on '18ests with potential upside to \n2018 [PS from —25-40% and stocks still cheap vs. discretionary. \n• Price action and sentiment keeps us constructive, we like the long and would expect US financials to benefit from \nany beta chase into year end. \n• How to play it? We still like \"appearing\" call spreads on XLF \no Buy a 6 month 105% call with a short 110% call that knock in if XLF trades above 115% during the life of the trade \nfor 1.75% premium cost \n• Gross max payoff if knock-in is triggered: 2.8x (5.0%/1.75%) \n• Gross max payoff if knock-in is not triggered: 5.6x (9.9%/1.75%) — you have upside up to 114.9%"
      },
      {
        "section_index": 7,
        "section_type": "document_footer",
        "text": "HOUSE OVERSIGHT 011280"
      },
      {
        "section_index": 8,
        "section_type": "signature",
        "text": "Regards, \nAmanda \nAmanda Ens \nDirector Global Equities \nBank of America Merrill Lynch \nMerrill Lynch, Pierce, Fenner & Smith Incorporated \nOne Bryant Park 15th Floor New York, NY 10036 \nPhone Mobile"
      },
      {
        "section_index": 9,
        "section_type": "email_header",
        "text": "From: Ens, Amanda \nSent: Tuesday, November 22, 2016 2:15 PM \nTo: 'jeffrey E.'; Rich Kahn \nSubject: Financials: buy XLF call spreads"
      },
      {
        "section_index": 10,
        "section_type": "paragraph",
        "text": "Underweight positioning, buybacks resuming, positive momentum and strong fundamentals all indicate that there is still \nfurther upside potential in financials (more details below). Our financials sector specialist thinks XLF could have another \n20-25% upside given the many levers to the Trump Trade: less regulation, higher interest rates, higher vol, economic \ngrowth, loan growth, etc. The asset sensitive regional banks are more of a pure play on a rates move but we view the \nlarger cap banks as having multi-pronged upside given the aforementioned points. \nThat said, given the velocity and magnitude of the recent move and uncertainty around the impact and timing of \nTrump's policies, we believe options offer better risk-reward than being outright long financials stocks here. With flat \ncall skew, \"appearing\" call spreads with upside knock-ins price well."
      },
      {
        "section_index": 11,
        "section_type": "paragraph",
        "text": "Buy a 1 year XLF call spread for 2.6% premium"
      },
      {
        "section_index": 12,
        "section_type": "list",
        "text": "• Buy a 110% call \n• Sell a 117.5% call with an at-expiry knock-in at 125% (call is not active unless XLF is 125% or higher at expiry) \no Total premium is 2.6% \no Gross max payoff if knock-in is triggered: 2.9x (7.5%/2.6%) \no Gross max payoff if knock-in is not triggered: 5.7x (14.9%/2.6%) — you have upside up to 124.9%"
      },
      {
        "section_index": 13,
        "section_type": "paragraph",
        "text": "Post Election Flow Skews - Buyers of Health Care (via ETFs) and Financials (mainly ETFs) \n• US Buyback Flows \n• Cons Disc, Technology and Financials are the largest 3 sectors for US buybacks (over 70% of execution). We \nare seeing a seasonal increase in buybacks as we come out of the low seasonal month of the year (October) and should \nsee increased buyback executions until year-end, another source of upside for the Cons Disc, Technology and Financials  \nsectors.  \nGlobal Positioning, Nigel Tupper, 11/14. Large long-only funds are more underweight Financials than any other \nsector and are UW this sector in all regions. \nFuture of Financials conference hosted 90 public and private companies at our Future of Financials conference. We are \nraising our price objectives across most of our names. Three primary reasons why we think there is upside remaining"
      },
      {
        "section_index": 14,
        "section_type": "document_footer",
        "text": "HOUSE OVERSIGHT 011281"
      },
      {
        "section_index": 15,
        "section_type": "paragraph",
        "text": "after the recent rally: 1) an improved outlook on both activity levels and interest rates, driving revenue upside; 2) \npotentially lower regulatory burden, particularly as new supervisory leadership can come with the new administration; \nand 3) relatively lighter positioning in US financials vs. other sectors. (Erika Najarian) \nTrades Gaining Momentum: Finance-Related Assets vs. S&P 500 \nIn the period since the US presidential election, the three top-performing S&P sectors and industry groups have all been \nfinance-related (Banks, Financials, Diversified Financials) \nSource: Kensho Technologies \nThe Flow Show, Michael Hartnett, 11/18. Violent rotation: record equity ETF inflow, record financials inflow, biggest \nbond outflow in 3.5 yrs, record EM debt outflow."
      },
      {
        "section_index": 16,
        "section_type": "signature",
        "text": "Regards, \nAmanda \nAmanda Ens \nDirector 1 Global Equities \nBank of America Merrill Lynch \nMerrill Lynch, Pierce, Fenner & Smith Incorporated \nOne Bryant Park 15th Floor New York, NY 10036 \nPhone: Mobile:"
      },
      {
        "section_index": 17,
        "section_type": "disclaimer",
        "text": "This message, and any attachments, is for the intended recipient(s) only, may contain information that is \nprivileged, confidential and/or proprietary and subject to important terms and conditions available at"
      },
      {
        "section_index": 18,
        "section_type": "document_footer",
        "text": "HOUSE OVERSIGHT 011282"
      },
      {
        "section_index": 19,
        "section_type": "disclaimer",
        "text": "http://www.bankofamerica.com/emaildisclaimer. If you are not the intended recipient, please delete this \nmessage."
      },
      {
        "section_index": 20,
        "section_type": "disclaimer",
        "text": "please note \nThe information contained in this communication is \nconfidential, may be attorney-client privileged, may \nconstitute inside information, and is intended only for \nthe use of the addressee. It is the property of \nJEE \nUnauthorized use, disclosure or copying of this \ncommunication or any part thereof is strictly prohibited \nand may be unlawful. If you have received this \ncommunication in error, please notify us immediately by \nreturn e-mail or by e-mail to jeevacation@gmail.com, and \ndestroy this communication and all copies thereof, \nincluding all attachments. copyright -all rights reserved"
      },
      {
        "section_index": 21,
        "section_type": "disclaimer",
        "text": "This message, and any attachments, is for the intended recipient(s) only, may contain information that is \nprivileged, confidential and/or proprietary and subject to important terms and conditions available at \nhttp://www.bankofamerica.com/emaildisclaimer. If you are not the intended recipient, please delete this \nmessage."
      },
      {
        "section_index": 22,
        "section_type": "document_footer",
        "text": "HOUSE OVERSIGHT 011283"
      }
    ]
  },
  "metadata": {
    "document_type": "Email Chain",
    "participants": [
      "Ens, Amanda",
      "jeffrey E.",
      "Richard Kah",
      "Richard Kahn",
      "Rich Kahn"
    ],
    "date_range": {
      "earliest": "2016-11-22",
      "latest": "2016-12-09"
    },
    "file_references": [
      "HOUSE OVERSIGHT 011280",
      "HOUSE OVERSIGHT 011281",
      "HOUSE OVERSIGHT 011282",
      "HOUSE OVERSIGHT 011283"
    ]
  },
  "entities": {
    "people": [
      "Ens, Amanda",
      "jeffrey E.",
      "Richard Kah",
      "Richard Kahn",
      "Rich Kahn",
      "Erika Najarian",
      "Reagan",
      "Trump",
      "Nigel Tupper",
      "Michael Hartnett"
    ],
    "organizations": [
      "Bank of America Merrill Lynch",
      "Merrill Lynch, Pierce, Fenner & Smith Incorporated",
      "BAML",
      "S&P",
      "JEE",
      "Kensho Technologies",
      "House Oversight Committee"
    ],
    "locations": [
      "North American",
      "US",
      "One Bryant Park 15th Floor New York, NY 10036"
    ],
    "dates": [
      "12/9/2016 4:03:45 PM",
      "Friday, December 09, 2016 10:56 AM",
      "Fri, Dec 9, 2016 at 11:46 AM",
      "Thanksgiving",
      "1986",
      "2003",
      "2004",
      "2018",
      "year end",
      "Tuesday, November 22, 2016 2:15 PM",
      "October",
      "11/14",
      "11/18"
    ],
    "events": [
      "buy XLF call spreads",
      "marketing trip",
      "Reagan's tax reform bill passed the Senate",
      "US presidential election",
      "Trump Trade",
      "Future of Financials conference",
      "The Flow Show"
    ]
  },
  "themes": [
    "Financial Sector Investment Strategy",
    "Options Trading",
    "XLF Call Spreads",
    "Post-Election Market Analysis",
    "Impact of Trump Administration Policies",
    "Investor Sentiment",
    "Bank Stocks"
  ],
  "confidence": 0.98,
  "notes": "The document is an email chain discussing investment strategies in the financial sector, specifically buying XLF call spreads, shortly after the 2016 US presidential election. The name of one participant is spelled inconsistently ('Richard Kah', 'Richard Kahn', 'Rich Kahn'). The text contains formatting markers like long underscores and page/Bates numbers ('HOUSE OVERSIGHT XXXXXX') at the bottom of each page, indicating it's part of a larger document production. The email from Jeffrey E. has two different email addresses associated with it: jeeyacation@gmail.com and jeevacation@gmail.com.",
  "file_path": "TEXT\\001\\HOUSE_OVERSIGHT_011280.txt",
  "house_oversight_id": "011280",
  "processing_metadata": {
    "processed_at": "2025-11-14T01:46:25.344181Z",
    "model": "gemini-2.5-pro"
  }
}